{"row":15,"col":15,"BL_Nodes":[{"Position":{"x":0.5,"y":0.5,"z":0.0},"Node_Type":0},{"Position":{"x":0.5,"y":1.5,"z":0.0},"Node_Type":0},{"Position":{"x":0.5,"y":2.5,"z":0.0},"Node_Type":0},{"Position":{"x":0.5,"y":3.5,"z":0.0},"Node_Type":0},{"Position":{"x":0.5,"y":4.5,"z":0.0},"Node_Type":0},{"Position":{"x":0.5,"y":5.5,"z":0.0},"Node_Type":0},{"Position":{"x":0.5,"y":6.5,"z":0.0},"Node_Type":0},{"Position":{"x":0.5,"y":7.5,"z":0.0},"Node_Type":0},{"Position":{"x":0.5,"y":8.5,"z":0.0},"Node_Type":0},{"Position":{"x":0.5,"y":9.5,"z":0.0},"Node_Type":0},{"Position":{"x":0.5,"y":10.5,"z":0.0},"Node_Type":0},{"Position":{"x":0.5,"y":11.5,"z":0.0},"Node_Type":0},{"Position":{"x":0.5,"y":12.5,"z":0.0},"Node_Type":0},{"Position":{"x":0.5,"y":13.5,"z":0.0},"Node_Type":0},{"Position":{"x":1.5,"y":0.5,"z":0.0},"Node_Type":0},{"Position":{"x":1.5,"y":1.5,"z":0.0},"Node_Type":0},{"Position":{"x":1.5,"y":2.5,"z":0.0},"Node_Type":0},{"Position":{"x":1.5,"y":3.5,"z":0.0},"Node_Type":0},{"Position":{"x":1.5,"y":4.5,"z":0.0},"Node_Type":0},{"Position":{"x":1.5,"y":5.5,"z":0.0},"Node_Type":0},{"Position":{"x":1.5,"y":6.5,"z":0.0},"Node_Type":0},{"Position":{"x":1.5,"y":7.5,"z":0.0},"Node_Type":0},{"Position":{"x":1.5,"y":8.5,"z":0.0},"Node_Type":0},{"Position":{"x":1.5,"y":9.5,"z":0.0},"Node_Type":0},{"Position":{"x":1.5,"y":10.5,"z":0.0},"Node_Type":0},{"Position":{"x":1.5,"y":11.5,"z":0.0},"Node_Type":0},{"Position":{"x":1.5,"y":12.5,"z":0.0},"Node_Type":0},{"Position":{"x":1.5,"y":13.5,"z":0.0},"Node_Type":0},{"Position":{"x":2.5,"y":0.5,"z":0.0},"Node_Type":0},{"Position":{"x":2.5,"y":1.5,"z":0.0},"Node_Type":0},{"Position":{"x":2.5,"y":2.5,"z":0.0},"Node_Type":0},{"Position":{"x":2.5,"y":3.5,"z":0.0},"Node_Type":0},{"Position":{"x":2.5,"y":4.5,"z":0.0},"Node_Type":0},{"Position":{"x":2.5,"y":5.5,"z":0.0},"Node_Type":0},{"Position":{"x":2.5,"y":6.5,"z":0.0},"Node_Type":0},{"Position":{"x":2.5,"y":7.5,"z":0.0},"Node_Type":0},{"Position":{"x":2.5,"y":8.5,"z":0.0},"Node_Type":0},{"Position":{"x":2.5,"y":9.5,"z":0.0},"Node_Type":0},{"Position":{"x":2.5,"y":10.5,"z":0.0},"Node_Type":0},{"Position":{"x":2.5,"y":11.5,"z":0.0},"Node_Type":0},{"Position":{"x":2.5,"y":12.5,"z":0.0},"Node_Type":0},{"Position":{"x":2.5,"y":13.5,"z":0.0},"Node_Type":0},{"Position":{"x":3.5,"y":0.5,"z":0.0},"Node_Type":0},{"Position":{"x":3.5,"y":1.5,"z":0.0},"Node_Type":0},{"Position":{"x":3.5,"y":2.5,"z":0.0},"Node_Type":0},{"Position":{"x":3.5,"y":3.5,"z":0.0},"Node_Type":0},{"Position":{"x":3.5,"y":4.5,"z":0.0},"Node_Type":0},{"Position":{"x":3.5,"y":5.5,"z":0.0},"Node_Type":0},{"Position":{"x":3.5,"y":6.5,"z":0.0},"Node_Type":0},{"Position":{"x":3.5,"y":7.5,"z":0.0},"Node_Type":0},{"Position":{"x":3.5,"y":8.5,"z":0.0},"Node_Type":0},{"Position":{"x":3.5,"y":9.5,"z":0.0},"Node_Type":0},{"Position":{"x":3.5,"y":10.5,"z":0.0},"Node_Type":0},{"Position":{"x":3.5,"y":11.5,"z":0.0},"Node_Type":0},{"Position":{"x":3.5,"y":12.5,"z":0.0},"Node_Type":0},{"Position":{"x":3.5,"y":13.5,"z":0.0},"Node_Type":0},{"Position":{"x":4.5,"y":0.5,"z":0.0},"Node_Type":0},{"Position":{"x":4.5,"y":1.5,"z":0.0},"Node_Type":0},{"Position":{"x":4.5,"y":2.5,"z":0.0},"Node_Type":0},{"Position":{"x":4.5,"y":3.5,"z":0.0},"Node_Type":0},{"Position":{"x":4.5,"y":4.5,"z":0.0},"Node_Type":0},{"Position":{"x":4.5,"y":5.5,"z":0.0},"Node_Type":0},{"Position":{"x":4.5,"y":6.5,"z":0.0},"Node_Type":0},{"Position":{"x":4.5,"y":7.5,"z":0.0},"Node_Type":0},{"Position":{"x":4.5,"y":8.5,"z":0.0},"Node_Type":0},{"Position":{"x":4.5,"y":9.5,"z":0.0},"Node_Type":0},{"Position":{"x":4.5,"y":10.5,"z":0.0},"Node_Type":0},{"Position":{"x":4.5,"y":11.5,"z":0.0},"Node_Type":0},{"Position":{"x":4.5,"y":12.5,"z":0.0},"Node_Type":0},{"Position":{"x":4.5,"y":13.5,"z":0.0},"Node_Type":0},{"Position":{"x":5.5,"y":0.5,"z":0.0},"Node_Type":0},{"Position":{"x":5.5,"y":1.5,"z":0.0},"Node_Type":0},{"Position":{"x":5.5,"y":2.5,"z":0.0},"Node_Type":0},{"Position":{"x":5.5,"y":3.5,"z":0.0},"Node_Type":0},{"Position":{"x":5.5,"y":4.5,"z":0.0},"Node_Type":0},{"Position":{"x":5.5,"y":5.5,"z":0.0},"Node_Type":0},{"Position":{"x":5.5,"y":6.5,"z":0.0},"Node_Type":0},{"Position":{"x":5.5,"y":7.5,"z":0.0},"Node_Type":0},{"Position":{"x":5.5,"y":8.5,"z":0.0},"Node_Type":0},{"Position":{"x":5.5,"y":9.5,"z":0.0},"Node_Type":0},{"Position":{"x":5.5,"y":10.5,"z":0.0},"Node_Type":0},{"Position":{"x":5.5,"y":11.5,"z":0.0},"Node_Type":0},{"Position":{"x":5.5,"y":12.5,"z":0.0},"Node_Type":0},{"Position":{"x":5.5,"y":13.5,"z":0.0},"Node_Type":0},{"Position":{"x":6.5,"y":0.5,"z":0.0},"Node_Type":0},{"Position":{"x":6.5,"y":1.5,"z":0.0},"Node_Type":0},{"Position":{"x":6.5,"y":2.5,"z":0.0},"Node_Type":0},{"Position":{"x":6.5,"y":3.5,"z":0.0},"Node_Type":0},{"Position":{"x":6.5,"y":4.5,"z":0.0},"Node_Type":0},{"Position":{"x":6.5,"y":5.5,"z":0.0},"Node_Type":0},{"Position":{"x":6.5,"y":6.5,"z":0.0},"Node_Type":0},{"Position":{"x":6.5,"y":7.5,"z":0.0},"Node_Type":0},{"Position":{"x":6.5,"y":8.5,"z":0.0},"Node_Type":0},{"Position":{"x":6.5,"y":9.5,"z":0.0},"Node_Type":0},{"Position":{"x":6.5,"y":10.5,"z":0.0},"Node_Type":0},{"Position":{"x":6.5,"y":11.5,"z":0.0},"Node_Type":0},{"Position":{"x":6.5,"y":12.5,"z":0.0},"Node_Type":0},{"Position":{"x":6.5,"y":13.5,"z":0.0},"Node_Type":0},{"Position":{"x":7.5,"y":0.5,"z":0.0},"Node_Type":0},{"Position":{"x":7.5,"y":1.5,"z":0.0},"Node_Type":0},{"Position":{"x":7.5,"y":2.5,"z":0.0},"Node_Type":0},{"Position":{"x":7.5,"y":3.5,"z":0.0},"Node_Type":0},{"Position":{"x":7.5,"y":4.5,"z":0.0},"Node_Type":0},{"Position":{"x":7.5,"y":5.5,"z":0.0},"Node_Type":0},{"Position":{"x":7.5,"y":6.5,"z":0.0},"Node_Type":0},{"Position":{"x":7.5,"y":7.5,"z":0.0},"Node_Type":0},{"Position":{"x":7.5,"y":8.5,"z":0.0},"Node_Type":0},{"Position":{"x":7.5,"y":9.5,"z":0.0},"Node_Type":0},{"Position":{"x":7.5,"y":10.5,"z":0.0},"Node_Type":0},{"Position":{"x":7.5,"y":11.5,"z":0.0},"Node_Type":0},{"Position":{"x":7.5,"y":12.5,"z":0.0},"Node_Type":0},{"Position":{"x":7.5,"y":13.5,"z":0.0},"Node_Type":0},{"Position":{"x":8.5,"y":0.5,"z":0.0},"Node_Type":0},{"Position":{"x":8.5,"y":1.5,"z":0.0},"Node_Type":0},{"Position":{"x":8.5,"y":2.5,"z":0.0},"Node_Type":0},{"Position":{"x":8.5,"y":3.5,"z":0.0},"Node_Type":0},{"Position":{"x":8.5,"y":4.5,"z":0.0},"Node_Type":0},{"Position":{"x":8.5,"y":5.5,"z":0.0},"Node_Type":0},{"Position":{"x":8.5,"y":6.5,"z":0.0},"Node_Type":0},{"Position":{"x":8.5,"y":7.5,"z":0.0},"Node_Type":0},{"Position":{"x":8.5,"y":8.5,"z":0.0},"Node_Type":0},{"Position":{"x":8.5,"y":9.5,"z":0.0},"Node_Type":0},{"Position":{"x":8.5,"y":10.5,"z":0.0},"Node_Type":0},{"Position":{"x":8.5,"y":11.5,"z":0.0},"Node_Type":0},{"Position":{"x":8.5,"y":12.5,"z":0.0},"Node_Type":0},{"Position":{"x":8.5,"y":13.5,"z":0.0},"Node_Type":0},{"Position":{"x":9.5,"y":0.5,"z":0.0},"Node_Type":0},{"Position":{"x":9.5,"y":1.5,"z":0.0},"Node_Type":0},{"Position":{"x":9.5,"y":2.5,"z":0.0},"Node_Type":0},{"Position":{"x":9.5,"y":3.5,"z":0.0},"Node_Type":0},{"Position":{"x":9.5,"y":4.5,"z":0.0},"Node_Type":0},{"Position":{"x":9.5,"y":5.5,"z":0.0},"Node_Type":0},{"Position":{"x":9.5,"y":6.5,"z":0.0},"Node_Type":0},{"Position":{"x":9.5,"y":7.5,"z":0.0},"Node_Type":0},{"Position":{"x":9.5,"y":8.5,"z":0.0},"Node_Type":0},{"Position":{"x":9.5,"y":9.5,"z":0.0},"Node_Type":0},{"Position":{"x":9.5,"y":10.5,"z":0.0},"Node_Type":0},{"Position":{"x":9.5,"y":11.5,"z":0.0},"Node_Type":0},{"Position":{"x":9.5,"y":12.5,"z":0.0},"Node_Type":0},{"Position":{"x":9.5,"y":13.5,"z":0.0},"Node_Type":0},{"Position":{"x":10.5,"y":0.5,"z":0.0},"Node_Type":0},{"Position":{"x":10.5,"y":1.5,"z":0.0},"Node_Type":0},{"Position":{"x":10.5,"y":2.5,"z":0.0},"Node_Type":0},{"Position":{"x":10.5,"y":3.5,"z":0.0},"Node_Type":0},{"Position":{"x":10.5,"y":4.5,"z":0.0},"Node_Type":0},{"Position":{"x":10.5,"y":5.5,"z":0.0},"Node_Type":0},{"Position":{"x":10.5,"y":6.5,"z":0.0},"Node_Type":0},{"Position":{"x":10.5,"y":7.5,"z":0.0},"Node_Type":0},{"Position":{"x":10.5,"y":8.5,"z":0.0},"Node_Type":0},{"Position":{"x":10.5,"y":9.5,"z":0.0},"Node_Type":0},{"Position":{"x":10.5,"y":10.5,"z":0.0},"Node_Type":0},{"Position":{"x":10.5,"y":11.5,"z":0.0},"Node_Type":0},{"Position":{"x":10.5,"y":12.5,"z":0.0},"Node_Type":0},{"Position":{"x":10.5,"y":13.5,"z":0.0},"Node_Type":0},{"Position":{"x":11.5,"y":0.5,"z":0.0},"Node_Type":0},{"Position":{"x":11.5,"y":1.5,"z":0.0},"Node_Type":0},{"Position":{"x":11.5,"y":2.5,"z":0.0},"Node_Type":0},{"Position":{"x":11.5,"y":3.5,"z":0.0},"Node_Type":0},{"Position":{"x":11.5,"y":4.5,"z":0.0},"Node_Type":0},{"Position":{"x":11.5,"y":5.5,"z":0.0},"Node_Type":0},{"Position":{"x":11.5,"y":6.5,"z":0.0},"Node_Type":0},{"Position":{"x":11.5,"y":7.5,"z":0.0},"Node_Type":0},{"Position":{"x":11.5,"y":8.5,"z":0.0},"Node_Type":0},{"Position":{"x":11.5,"y":9.5,"z":0.0},"Node_Type":0},{"Position":{"x":11.5,"y":10.5,"z":0.0},"Node_Type":0},{"Position":{"x":11.5,"y":11.5,"z":0.0},"Node_Type":0},{"Position":{"x":11.5,"y":12.5,"z":0.0},"Node_Type":0},{"Position":{"x":11.5,"y":13.5,"z":0.0},"Node_Type":0},{"Position":{"x":12.5,"y":0.5,"z":0.0},"Node_Type":0},{"Position":{"x":12.5,"y":1.5,"z":0.0},"Node_Type":0},{"Position":{"x":12.5,"y":2.5,"z":0.0},"Node_Type":0},{"Position":{"x":12.5,"y":3.5,"z":0.0},"Node_Type":0},{"Position":{"x":12.5,"y":4.5,"z":0.0},"Node_Type":0},{"Position":{"x":12.5,"y":5.5,"z":0.0},"Node_Type":0},{"Position":{"x":12.5,"y":6.5,"z":0.0},"Node_Type":0},{"Position":{"x":12.5,"y":7.5,"z":0.0},"Node_Type":0},{"Position":{"x":12.5,"y":8.5,"z":0.0},"Node_Type":0},{"Position":{"x":12.5,"y":9.5,"z":0.0},"Node_Type":0},{"Position":{"x":12.5,"y":10.5,"z":0.0},"Node_Type":0},{"Position":{"x":12.5,"y":11.5,"z":0.0},"Node_Type":0},{"Position":{"x":12.5,"y":12.5,"z":0.0},"Node_Type":0},{"Position":{"x":12.5,"y":13.5,"z":0.0},"Node_Type":0},{"Position":{"x":13.5,"y":0.5,"z":0.0},"Node_Type":0},{"Position":{"x":13.5,"y":1.5,"z":0.0},"Node_Type":0},{"Position":{"x":13.5,"y":2.5,"z":0.0},"Node_Type":0},{"Position":{"x":13.5,"y":3.5,"z":0.0},"Node_Type":0},{"Position":{"x":13.5,"y":4.5,"z":0.0},"Node_Type":0},{"Position":{"x":13.5,"y":5.5,"z":0.0},"Node_Type":0},{"Position":{"x":13.5,"y":6.5,"z":0.0},"Node_Type":0},{"Position":{"x":13.5,"y":7.5,"z":0.0},"Node_Type":0},{"Position":{"x":13.5,"y":8.5,"z":0.0},"Node_Type":0},{"Position":{"x":13.5,"y":9.5,"z":0.0},"Node_Type":0},{"Position":{"x":13.5,"y":10.5,"z":0.0},"Node_Type":0},{"Position":{"x":13.5,"y":11.5,"z":0.0},"Node_Type":0},{"Position":{"x":13.5,"y":12.5,"z":0.0},"Node_Type":0},{"Position":{"x":13.5,"y":13.5,"z":0.0},"Node_Type":0}],"LI_Nodes":[{"Position":{"x":0.0,"y":0.0,"z":0.0},"Node_Type":0},{"Position":{"x":0.0,"y":1.0,"z":0.0},"Node_Type":0},{"Position":{"x":0.0,"y":2.0,"z":0.0},"Node_Type":0},{"Position":{"x":0.0,"y":3.0,"z":0.0},"Node_Type":0},{"Position":{"x":0.0,"y":4.0,"z":0.0},"Node_Type":0},{"Position":{"x":0.0,"y":5.0,"z":0.0},"Node_Type":0},{"Position":{"x":0.0,"y":6.0,"z":0.0},"Node_Type":0},{"Position":{"x":0.0,"y":7.0,"z":0.0},"Node_Type":0},{"Position":{"x":0.0,"y":8.0,"z":0.0},"Node_Type":0},{"Position":{"x":0.0,"y":9.0,"z":0.0},"Node_Type":0},{"Position":{"x":0.0,"y":10.0,"z":0.0},"Node_Type":0},{"Position":{"x":0.0,"y":11.0,"z":0.0},"Node_Type":0},{"Position":{"x":0.0,"y":12.0,"z":0.0},"Node_Type":0},{"Position":{"x":0.0,"y":13.0,"z":0.0},"Node_Type":0},{"Position":{"x":0.0,"y":14.0,"z":0.0},"Node_Type":0},{"Position":{"x":1.0,"y":0.0,"z":0.0},"Node_Type":0},{"Position":{"x":1.0,"y":1.0,"z":0.0},"Node_Type":0},{"Position":{"x":1.0,"y":2.0,"z":0.0},"Node_Type":0},{"Position":{"x":1.0,"y":3.0,"z":0.0},"Node_Type":0},{"Position":{"x":1.0,"y":4.0,"z":0.0},"Node_Type":0},{"Position":{"x":1.0,"y":5.0,"z":0.0},"Node_Type":0},{"Position":{"x":1.0,"y":6.0,"z":0.0},"Node_Type":7},{"Position":{"x":1.0,"y":7.0,"z":0.0},"Node_Type":8},{"Position":{"x":1.0,"y":8.0,"z":0.0},"Node_Type":8},{"Position":{"x":1.0,"y":9.0,"z":0.0},"Node_Type":8},{"Position":{"x":1.0,"y":10.0,"z":0.0},"Node_Type":8},{"Position":{"x":1.0,"y":11.0,"z":0.0},"Node_Type":8},{"Position":{"x":1.0,"y":12.0,"z":0.0},"Node_Type":8},{"Position":{"x":1.0,"y":13.0,"z":0.0},"Node_Type":8},{"Position":{"x":1.0,"y":14.0,"z":0.0},"Node_Type":0},{"Position":{"x":2.0,"y":0.0,"z":0.0},"Node_Type":0},{"Position":{"x":2.0,"y":1.0,"z":0.0},"Node_Type":0},{"Position":{"x":2.0,"y":2.0,"z":0.0},"Node_Type":0},{"Position":{"x":2.0,"y":3.0,"z":0.0},"Node_Type":0},{"Position":{"x":2.0,"y":4.0,"z":0.0},"Node_Type":0},{"Position":{"x":2.0,"y":5.0,"z":0.0},"Node_Type":0},{"Position":{"x":2.0,"y":6.0,"z":0.0},"Node_Type":0},{"Position":{"x":2.0,"y":7.0,"z":0.0},"Node_Type":0},{"Position":{"x":2.0,"y":8.0,"z":0.0},"Node_Type":0},{"Position":{"x":2.0,"y":9.0,"z":0.0},"Node_Type":0},{"Position":{"x":2.0,"y":10.0,"z":0.0},"Node_Type":0},{"Position":{"x":2.0,"y":11.0,"z":0.0},"Node_Type":0},{"Position":{"x":2.0,"y":12.0,"z":0.0},"Node_Type":0},{"Position":{"x":2.0,"y":13.0,"z":0.0},"Node_Type":8},{"Position":{"x":2.0,"y":14.0,"z":0.0},"Node_Type":0},{"Position":{"x":3.0,"y":0.0,"z":0.0},"Node_Type":0},{"Position":{"x":3.0,"y":1.0,"z":0.0},"Node_Type":0},{"Position":{"x":3.0,"y":2.0,"z":0.0},"Node_Type":0},{"Position":{"x":3.0,"y":3.0,"z":0.0},"Node_Type":0},{"Position":{"x":3.0,"y":4.0,"z":0.0},"Node_Type":0},{"Position":{"x":3.0,"y":5.0,"z":0.0},"Node_Type":0},{"Position":{"x":3.0,"y":6.0,"z":0.0},"Node_Type":0},{"Position":{"x":3.0,"y":7.0,"z":0.0},"Node_Type":0},{"Position":{"x":3.0,"y":8.0,"z":0.0},"Node_Type":0},{"Position":{"x":3.0,"y":9.0,"z":0.0},"Node_Type":0},{"Position":{"x":3.0,"y":10.0,"z":0.0},"Node_Type":0},{"Position":{"x":3.0,"y":11.0,"z":0.0},"Node_Type":0},{"Position":{"x":3.0,"y":12.0,"z":0.0},"Node_Type":0},{"Position":{"x":3.0,"y":13.0,"z":0.0},"Node_Type":8},{"Position":{"x":3.0,"y":14.0,"z":0.0},"Node_Type":0},{"Position":{"x":4.0,"y":0.0,"z":0.0},"Node_Type":0},{"Position":{"x":4.0,"y":1.0,"z":0.0},"Node_Type":0},{"Position":{"x":4.0,"y":2.0,"z":0.0},"Node_Type":0},{"Position":{"x":4.0,"y":3.0,"z":0.0},"Node_Type":0},{"Position":{"x":4.0,"y":4.0,"z":0.0},"Node_Type":0},{"Position":{"x":4.0,"y":5.0,"z":0.0},"Node_Type":0},{"Position":{"x":4.0,"y":6.0,"z":0.0},"Node_Type":0},{"Position":{"x":4.0,"y":7.0,"z":0.0},"Node_Type":0},{"Position":{"x":4.0,"y":8.0,"z":0.0},"Node_Type":0},{"Position":{"x":4.0,"y":9.0,"z":0.0},"Node_Type":0},{"Position":{"x":4.0,"y":10.0,"z":0.0},"Node_Type":0},{"Position":{"x":4.0,"y":11.0,"z":0.0},"Node_Type":0},{"Position":{"x":4.0,"y":12.0,"z":0.0},"Node_Type":0},{"Position":{"x":4.0,"y":13.0,"z":0.0},"Node_Type":8},{"Position":{"x":4.0,"y":14.0,"z":0.0},"Node_Type":0},{"Position":{"x":5.0,"y":0.0,"z":0.0},"Node_Type":0},{"Position":{"x":5.0,"y":1.0,"z":0.0},"Node_Type":0},{"Position":{"x":5.0,"y":2.0,"z":0.0},"Node_Type":0},{"Position":{"x":5.0,"y":3.0,"z":0.0},"Node_Type":0},{"Position":{"x":5.0,"y":4.0,"z":0.0},"Node_Type":0},{"Position":{"x":5.0,"y":5.0,"z":0.0},"Node_Type":0},{"Position":{"x":5.0,"y":6.0,"z":0.0},"Node_Type":0},{"Position":{"x":5.0,"y":7.0,"z":0.0},"Node_Type":0},{"Position":{"x":5.0,"y":8.0,"z":0.0},"Node_Type":0},{"Position":{"x":5.0,"y":9.0,"z":0.0},"Node_Type":0},{"Position":{"x":5.0,"y":10.0,"z":0.0},"Node_Type":0},{"Position":{"x":5.0,"y":11.0,"z":0.0},"Node_Type":0},{"Position":{"x":5.0,"y":12.0,"z":0.0},"Node_Type":0},{"Position":{"x":5.0,"y":13.0,"z":0.0},"Node_Type":8},{"Position":{"x":5.0,"y":14.0,"z":0.0},"Node_Type":0},{"Position":{"x":6.0,"y":0.0,"z":0.0},"Node_Type":0},{"Position":{"x":6.0,"y":1.0,"z":0.0},"Node_Type":10},{"Position":{"x":6.0,"y":2.0,"z":0.0},"Node_Type":0},{"Position":{"x":6.0,"y":3.0,"z":0.0},"Node_Type":0},{"Position":{"x":6.0,"y":4.0,"z":0.0},"Node_Type":0},{"Position":{"x":6.0,"y":5.0,"z":0.0},"Node_Type":0},{"Position":{"x":6.0,"y":6.0,"z":0.0},"Node_Type":0},{"Position":{"x":6.0,"y":7.0,"z":0.0},"Node_Type":3},{"Position":{"x":6.0,"y":8.0,"z":0.0},"Node_Type":4},{"Position":{"x":6.0,"y":9.0,"z":0.0},"Node_Type":0},{"Position":{"x":6.0,"y":10.0,"z":0.0},"Node_Type":0},{"Position":{"x":6.0,"y":11.0,"z":0.0},"Node_Type":0},{"Position":{"x":6.0,"y":12.0,"z":0.0},"Node_Type":0},{"Position":{"x":6.0,"y":13.0,"z":0.0},"Node_Type":8},{"Position":{"x":6.0,"y":14.0,"z":0.0},"Node_Type":0},{"Position":{"x":7.0,"y":0.0,"z":0.0},"Node_Type":0},{"Position":{"x":7.0,"y":1.0,"z":0.0},"Node_Type":10},{"Position":{"x":7.0,"y":2.0,"z":0.0},"Node_Type":3},{"Position":{"x":7.0,"y":3.0,"z":0.0},"Node_Type":0},{"Position":{"x":7.0,"y":4.0,"z":0.0},"Node_Type":0},{"Position":{"x":7.0,"y":5.0,"z":0.0},"Node_Type":0},{"Position":{"x":7.0,"y":6.0,"z":0.0},"Node_Type":0},{"Position":{"x":7.0,"y":7.0,"z":0.0},"Node_Type":0},{"Position":{"x":7.0,"y":8.0,"z":0.0},"Node_Type":0},{"Position":{"x":7.0,"y":9.0,"z":0.0},"Node_Type":0},{"Position":{"x":7.0,"y":10.0,"z":0.0},"Node_Type":0},{"Position":{"x":7.0,"y":11.0,"z":0.0},"Node_Type":0},{"Position":{"x":7.0,"y":12.0,"z":0.0},"Node_Type":4},{"Position":{"x":7.0,"y":13.0,"z":0.0},"Node_Type":8},{"Position":{"x":7.0,"y":14.0,"z":0.0},"Node_Type":0},{"Position":{"x":8.0,"y":0.0,"z":0.0},"Node_Type":0},{"Position":{"x":8.0,"y":1.0,"z":0.0},"Node_Type":10},{"Position":{"x":8.0,"y":2.0,"z":0.0},"Node_Type":0},{"Position":{"x":8.0,"y":3.0,"z":0.0},"Node_Type":0},{"Position":{"x":8.0,"y":4.0,"z":0.0},"Node_Type":0},{"Position":{"x":8.0,"y":5.0,"z":0.0},"Node_Type":0},{"Position":{"x":8.0,"y":6.0,"z":0.0},"Node_Type":3},{"Position":{"x":8.0,"y":7.0,"z":0.0},"Node_Type":4},{"Position":{"x":8.0,"y":8.0,"z":0.0},"Node_Type":0},{"Position":{"x":8.0,"y":9.0,"z":0.0},"Node_Type":0},{"Position":{"x":8.0,"y":10.0,"z":0.0},"Node_Type":0},{"Position":{"x":8.0,"y":11.0,"z":0.0},"Node_Type":0},{"Position":{"x":8.0,"y":12.0,"z":0.0},"Node_Type":0},{"Position":{"x":8.0,"y":13.0,"z":0.0},"Node_Type":8},{"Position":{"x":8.0,"y":14.0,"z":0.0},"Node_Type":0},{"Position":{"x":9.0,"y":0.0,"z":0.0},"Node_Type":0},{"Position":{"x":9.0,"y":1.0,"z":0.0},"Node_Type":10},{"Position":{"x":9.0,"y":2.0,"z":0.0},"Node_Type":0},{"Position":{"x":9.0,"y":3.0,"z":0.0},"Node_Type":0},{"Position":{"x":9.0,"y":4.0,"z":0.0},"Node_Type":0},{"Position":{"x":9.0,"y":5.0,"z":0.0},"Node_Type":0},{"Position":{"x":9.0,"y":6.0,"z":0.0},"Node_Type":0},{"Position":{"x":9.0,"y":7.0,"z":0.0},"Node_Type":0},{"Position":{"x":9.0,"y":8.0,"z":0.0},"Node_Type":0},{"Position":{"x":9.0,"y":9.0,"z":0.0},"Node_Type":0},{"Position":{"x":9.0,"y":10.0,"z":0.0},"Node_Type":0},{"Position":{"x":9.0,"y":11.0,"z":0.0},"Node_Type":0},{"Position":{"x":9.0,"y":12.0,"z":0.0},"Node_Type":0},{"Position":{"x":9.0,"y":13.0,"z":0.0},"Node_Type":0},{"Position":{"x":9.0,"y":14.0,"z":0.0},"Node_Type":0},{"Position":{"x":10.0,"y":0.0,"z":0.0},"Node_Type":0},{"Position":{"x":10.0,"y":1.0,"z":0.0},"Node_Type":10},{"Position":{"x":10.0,"y":2.0,"z":0.0},"Node_Type":0},{"Position":{"x":10.0,"y":3.0,"z":0.0},"Node_Type":0},{"Position":{"x":10.0,"y":4.0,"z":0.0},"Node_Type":0},{"Position":{"x":10.0,"y":5.0,"z":0.0},"Node_Type":0},{"Position":{"x":10.0,"y":6.0,"z":0.0},"Node_Type":0},{"Position":{"x":10.0,"y":7.0,"z":0.0},"Node_Type":0},{"Position":{"x":10.0,"y":8.0,"z":0.0},"Node_Type":0},{"Position":{"x":10.0,"y":9.0,"z":0.0},"Node_Type":0},{"Position":{"x":10.0,"y":10.0,"z":0.0},"Node_Type":0},{"Position":{"x":10.0,"y":11.0,"z":0.0},"Node_Type":0},{"Position":{"x":10.0,"y":12.0,"z":0.0},"Node_Type":0},{"Position":{"x":10.0,"y":13.0,"z":0.0},"Node_Type":0},{"Position":{"x":10.0,"y":14.0,"z":0.0},"Node_Type":0},{"Position":{"x":11.0,"y":0.0,"z":0.0},"Node_Type":0},{"Position":{"x":11.0,"y":1.0,"z":0.0},"Node_Type":10},{"Position":{"x":11.0,"y":2.0,"z":0.0},"Node_Type":0},{"Position":{"x":11.0,"y":3.0,"z":0.0},"Node_Type":0},{"Position":{"x":11.0,"y":4.0,"z":0.0},"Node_Type":0},{"Position":{"x":11.0,"y":5.0,"z":0.0},"Node_Type":0},{"Position":{"x":11.0,"y":6.0,"z":0.0},"Node_Type":0},{"Position":{"x":11.0,"y":7.0,"z":0.0},"Node_Type":0},{"Position":{"x":11.0,"y":8.0,"z":0.0},"Node_Type":0},{"Position":{"x":11.0,"y":9.0,"z":0.0},"Node_Type":0},{"Position":{"x":11.0,"y":10.0,"z":0.0},"Node_Type":0},{"Position":{"x":11.0,"y":11.0,"z":0.0},"Node_Type":0},{"Position":{"x":11.0,"y":12.0,"z":0.0},"Node_Type":0},{"Position":{"x":11.0,"y":13.0,"z":0.0},"Node_Type":0},{"Position":{"x":11.0,"y":14.0,"z":0.0},"Node_Type":0},{"Position":{"x":12.0,"y":0.0,"z":0.0},"Node_Type":0},{"Position":{"x":12.0,"y":1.0,"z":0.0},"Node_Type":10},{"Position":{"x":12.0,"y":2.0,"z":0.0},"Node_Type":0},{"Position":{"x":12.0,"y":3.0,"z":0.0},"Node_Type":0},{"Position":{"x":12.0,"y":4.0,"z":0.0},"Node_Type":0},{"Position":{"x":12.0,"y":5.0,"z":0.0},"Node_Type":0},{"Position":{"x":12.0,"y":6.0,"z":0.0},"Node_Type":0},{"Position":{"x":12.0,"y":7.0,"z":0.0},"Node_Type":0},{"Position":{"x":12.0,"y":8.0,"z":0.0},"Node_Type":0},{"Position":{"x":12.0,"y":9.0,"z":0.0},"Node_Type":0},{"Position":{"x":12.0,"y":10.0,"z":0.0},"Node_Type":0},{"Position":{"x":12.0,"y":11.0,"z":0.0},"Node_Type":0},{"Position":{"x":12.0,"y":12.0,"z":0.0},"Node_Type":0},{"Position":{"x":12.0,"y":13.0,"z":0.0},"Node_Type":0},{"Position":{"x":12.0,"y":14.0,"z":0.0},"Node_Type":0},{"Position":{"x":13.0,"y":0.0,"z":0.0},"Node_Type":0},{"Position":{"x":13.0,"y":1.0,"z":0.0},"Node_Type":10},{"Position":{"x":13.0,"y":2.0,"z":0.0},"Node_Type":10},{"Position":{"x":13.0,"y":3.0,"z":0.0},"Node_Type":10},{"Position":{"x":13.0,"y":4.0,"z":0.0},"Node_Type":10},{"Position":{"x":13.0,"y":5.0,"z":0.0},"Node_Type":10},{"Position":{"x":13.0,"y":6.0,"z":0.0},"Node_Type":10},{"Position":{"x":13.0,"y":7.0,"z":0.0},"Node_Type":10},{"Position":{"x":13.0,"y":8.0,"z":0.0},"Node_Type":9},{"Position":{"x":13.0,"y":9.0,"z":0.0},"Node_Type":0},{"Position":{"x":13.0,"y":10.0,"z":0.0},"Node_Type":0},{"Position":{"x":13.0,"y":11.0,"z":0.0},"Node_Type":0},{"Position":{"x":13.0,"y":12.0,"z":0.0},"Node_Type":0},{"Position":{"x":13.0,"y":13.0,"z":0.0},"Node_Type":0},{"Position":{"x":13.0,"y":14.0,"z":0.0},"Node_Type":0},{"Position":{"x":14.0,"y":0.0,"z":0.0},"Node_Type":0},{"Position":{"x":14.0,"y":1.0,"z":0.0},"Node_Type":0},{"Position":{"x":14.0,"y":2.0,"z":0.0},"Node_Type":0},{"Position":{"x":14.0,"y":3.0,"z":0.0},"Node_Type":0},{"Position":{"x":14.0,"y":4.0,"z":0.0},"Node_Type":0},{"Position":{"x":14.0,"y":5.0,"z":0.0},"Node_Type":0},{"Position":{"x":14.0,"y":6.0,"z":0.0},"Node_Type":0},{"Position":{"x":14.0,"y":7.0,"z":0.0},"Node_Type":0},{"Position":{"x":14.0,"y":8.0,"z":0.0},"Node_Type":0},{"Position":{"x":14.0,"y":9.0,"z":0.0},"Node_Type":0},{"Position":{"x":14.0,"y":10.0,"z":0.0},"Node_Type":0},{"Position":{"x":14.0,"y":11.0,"z":0.0},"Node_Type":0},{"Position":{"x":14.0,"y":12.0,"z":0.0},"Node_Type":0},{"Position":{"x":14.0,"y":13.0,"z":0.0},"Node_Type":0},{"Position":{"x":14.0,"y":14.0,"z":0.0},"Node_Type":0}],"BL_U_Edges":[{"Position":{"x":0.0,"y":0.5,"z":0.0},"Edge_Type":0,"Edge_Direction":0},{"Position":{"x":0.0,"y":1.5,"z":0.0},"Edge_Type":0,"Edge_Direction":0},{"Position":{"x":0.0,"y":2.5,"z":0.0},"Edge_Type":0,"Edge_Direction":0},{"Position":{"x":0.0,"y":3.5,"z":0.0},"Edge_Type":0,"Edge_Direction":0},{"Position":{"x":0.0,"y":4.5,"z":0.0},"Edge_Type":0,"Edge_Direction":0},{"Position":{"x":0.0,"y":5.5,"z":0.0},"Edge_Type":0,"Edge_Direction":0},{"Position":{"x":0.0,"y":6.5,"z":0.0},"Edge_Type":0,"Edge_Direction":0},{"Position":{"x":0.0,"y":7.5,"z":0.0},"Edge_Type":0,"Edge_Direction":0},{"Position":{"x":0.0,"y":8.5,"z":0.0},"Edge_Type":0,"Edge_Direction":0},{"Position":{"x":0.0,"y":9.5,"z":0.0},"Edge_Type":0,"Edge_Direction":0},{"Position":{"x":0.0,"y":10.5,"z":0.0},"Edge_Type":0,"Edge_Direction":0},{"Position":{"x":0.0,"y":11.5,"z":0.0},"Edge_Type":0,"Edge_Direction":0},{"Position":{"x":0.0,"y":12.5,"z":0.0},"Edge_Type":0,"Edge_Direction":0},{"Position":{"x":0.0,"y":13.5,"z":0.0},"Edge_Type":0,"Edge_Direction":0},{"Position":{"x":1.0,"y":0.5,"z":0.0},"Edge_Type":2,"Edge_Direction":0},{"Position":{"x":1.0,"y":1.5,"z":0.0},"Edge_Type":0,"Edge_Direction":0},{"Position":{"x":1.0,"y":2.5,"z":0.0},"Edge_Type":0,"Edge_Direction":0},{"Position":{"x":1.0,"y":3.5,"z":0.0},"Edge_Type":0,"Edge_Direction":0},{"Position":{"x":1.0,"y":4.5,"z":0.0},"Edge_Type":0,"Edge_Direction":0},{"Position":{"x":1.0,"y":5.5,"z":0.0},"Edge_Type":0,"Edge_Direction":0},{"Position":{"x":1.0,"y":6.5,"z":0.0},"Edge_Type":0,"Edge_Direction":0},{"Position":{"x":1.0,"y":7.5,"z":0.0},"Edge_Type":0,"Edge_Direction":0},{"Position":{"x":1.0,"y":8.5,"z":0.0},"Edge_Type":0,"Edge_Direction":0},{"Position":{"x":1.0,"y":9.5,"z":0.0},"Edge_Type":0,"Edge_Direction":0},{"Position":{"x":1.0,"y":10.5,"z":0.0},"Edge_Type":0,"Edge_Direction":0},{"Position":{"x":1.0,"y":11.5,"z":0.0},"Edge_Type":0,"Edge_Direction":0},{"Position":{"x":1.0,"y":12.5,"z":0.0},"Edge_Type":0,"Edge_Direction":0},{"Position":{"x":1.0,"y":13.5,"z":0.0},"Edge_Type":2,"Edge_Direction":0},{"Position":{"x":2.0,"y":0.5,"z":0.0},"Edge_Type":2,"Edge_Direction":0},{"Position":{"x":2.0,"y":1.5,"z":0.0},"Edge_Type":2,"Edge_Direction":0},{"Position":{"x":2.0,"y":2.5,"z":0.0},"Edge_Type":0,"Edge_Direction":0},{"Position":{"x":2.0,"y":3.5,"z":0.0},"Edge_Type":0,"Edge_Direction":0},{"Position":{"x":2.0,"y":4.5,"z":0.0},"Edge_Type":0,"Edge_Direction":0},{"Position":{"x":2.0,"y":5.5,"z":0.0},"Edge_Type":0,"Edge_Direction":0},{"Position":{"x":2.0,"y":6.5,"z":0.0},"Edge_Type":0,"Edge_Direction":0},{"Position":{"x":2.0,"y":7.5,"z":0.0},"Edge_Type":0,"Edge_Direction":0},{"Position":{"x":2.0,"y":8.5,"z":0.0},"Edge_Type":0,"Edge_Direction":0},{"Position":{"x":2.0,"y":9.5,"z":0.0},"Edge_Type":0,"Edge_Direction":0},{"Position":{"x":2.0,"y":10.5,"z":0.0},"Edge_Type":0,"Edge_Direction":0},{"Position":{"x":2.0,"y":11.5,"z":0.0},"Edge_Type":0,"Edge_Direction":0},{"Position":{"x":2.0,"y":12.5,"z":0.0},"Edge_Type":2,"Edge_Direction":0},{"Position":{"x":2.0,"y":13.5,"z":0.0},"Edge_Type":2,"Edge_Direction":0},{"Position":{"x":3.0,"y":0.5,"z":0.0},"Edge_Type":2,"Edge_Direction":0},{"Position":{"x":3.0,"y":1.5,"z":0.0},"Edge_Type":2,"Edge_Direction":0},{"Position":{"x":3.0,"y":2.5,"z":0.0},"Edge_Type":2,"Edge_Direction":0},{"Position":{"x":3.0,"y":3.5,"z":0.0},"Edge_Type":0,"Edge_Direction":0},{"Position":{"x":3.0,"y":4.5,"z":0.0},"Edge_Type":0,"Edge_Direction":0},{"Position":{"x":3.0,"y":5.5,"z":0.0},"Edge_Type":0,"Edge_Direction":0},{"Position":{"x":3.0,"y":6.5,"z":0.0},"Edge_Type":0,"Edge_Direction":0},{"Position":{"x":3.0,"y":7.5,"z":0.0},"Edge_Type":0,"Edge_Direction":0},{"Position":{"x":3.0,"y":8.5,"z":0.0},"Edge_Type":0,"Edge_Direction":0},{"Position":{"x":3.0,"y":9.5,"z":0.0},"Edge_Type":0,"Edge_Direction":0},{"Position":{"x":3.0,"y":10.5,"z":0.0},"Edge_Type":0,"Edge_Direction":0},{"Position":{"x":3.0,"y":11.5,"z":0.0},"Edge_Type":2,"Edge_Direction":0},{"Position":{"x":3.0,"y":12.5,"z":0.0},"Edge_Type":2,"Edge_Direction":0},{"Position":{"x":3.0,"y":13.5,"z":0.0},"Edge_Type":2,"Edge_Direction":0},{"Position":{"x":4.0,"y":0.5,"z":0.0},"Edge_Type":2,"Edge_Direction":0},{"Position":{"x":4.0,"y":1.5,"z":0.0},"Edge_Type":2,"Edge_Direction":0},{"Position":{"x":4.0,"y":2.5,"z":0.0},"Edge_Type":2,"Edge_Direction":0},{"Position":{"x":4.0,"y":3.5,"z":0.0},"Edge_Type":2,"Edge_Direction":0},{"Position":{"x":4.0,"y":4.5,"z":0.0},"Edge_Type":0,"Edge_Direction":0},{"Position":{"x":4.0,"y":5.5,"z":0.0},"Edge_Type":0,"Edge_Direction":0},{"Position":{"x":4.0,"y":6.5,"z":0.0},"Edge_Type":2,"Edge_Direction":0},{"Position":{"x":4.0,"y":7.5,"z":0.0},"Edge_Type":2,"Edge_Direction":0},{"Position":{"x":4.0,"y":8.5,"z":0.0},"Edge_Type":0,"Edge_Direction":0},{"Position":{"x":4.0,"y":9.5,"z":0.0},"Edge_Type":0,"Edge_Direction":0},{"Position":{"x":4.0,"y":10.5,"z":0.0},"Edge_Type":2,"Edge_Direction":0},{"Position":{"x":4.0,"y":11.5,"z":0.0},"Edge_Type":2,"Edge_Direction":0},{"Position":{"x":4.0,"y":12.5,"z":0.0},"Edge_Type":2,"Edge_Direction":0},{"Position":{"x":4.0,"y":13.5,"z":0.0},"Edge_Type":2,"Edge_Direction":0},{"Position":{"x":5.0,"y":0.5,"z":0.0},"Edge_Type":2,"Edge_Direction":0},{"Position":{"x":5.0,"y":1.5,"z":0.0},"Edge_Type":2,"Edge_Direction":0},{"Position":{"x":5.0,"y":2.5,"z":0.0},"Edge_Type":2,"Edge_Direction":0},{"Position":{"x":5.0,"y":3.5,"z":0.0},"Edge_Type":2,"Edge_Direction":0},{"Position":{"x":5.0,"y":4.5,"z":0.0},"Edge_Type":0,"Edge_Direction":0},{"Position":{"x":5.0,"y":5.5,"z":0.0},"Edge_Type":2,"Edge_Direction":0},{"Position":{"x":5.0,"y":6.5,"z":0.0},"Edge_Type":0,"Edge_Direction":0},{"Position":{"x":5.0,"y":7.5,"z":0.0},"Edge_Type":2,"Edge_Direction":0},{"Position":{"x":5.0,"y":8.5,"z":0.0},"Edge_Type":0,"Edge_Direction":0},{"Position":{"x":5.0,"y":9.5,"z":0.0},"Edge_Type":0,"Edge_Direction":0},{"Position":{"x":5.0,"y":10.5,"z":0.0},"Edge_Type":2,"Edge_Direction":0},{"Position":{"x":5.0,"y":11.5,"z":0.0},"Edge_Type":2,"Edge_Direction":0},{"Position":{"x":5.0,"y":12.5,"z":0.0},"Edge_Type":2,"Edge_Direction":0},{"Position":{"x":5.0,"y":13.5,"z":0.0},"Edge_Type":2,"Edge_Direction":0},{"Position":{"x":6.0,"y":0.5,"z":0.0},"Edge_Type":2,"Edge_Direction":0},{"Position":{"x":6.0,"y":1.5,"z":0.0},"Edge_Type":2,"Edge_Direction":0},{"Position":{"x":6.0,"y":2.5,"z":0.0},"Edge_Type":2,"Edge_Direction":0},{"Position":{"x":6.0,"y":3.5,"z":0.0},"Edge_Type":2,"Edge_Direction":0},{"Position":{"x":6.0,"y":4.5,"z":0.0},"Edge_Type":0,"Edge_Direction":0},{"Position":{"x":6.0,"y":5.5,"z":0.0},"Edge_Type":2,"Edge_Direction":0},{"Position":{"x":6.0,"y":6.5,"z":0.0},"Edge_Type":2,"Edge_Direction":0},{"Position":{"x":6.0,"y":7.5,"z":0.0},"Edge_Type":0,"Edge_Direction":0},{"Position":{"x":6.0,"y":8.5,"z":0.0},"Edge_Type":2,"Edge_Direction":0},{"Position":{"x":6.0,"y":9.5,"z":0.0},"Edge_Type":0,"Edge_Direction":0},{"Position":{"x":6.0,"y":10.5,"z":0.0},"Edge_Type":2,"Edge_Direction":0},{"Position":{"x":6.0,"y":11.5,"z":0.0},"Edge_Type":2,"Edge_Direction":0},{"Position":{"x":6.0,"y":12.5,"z":0.0},"Edge_Type":2,"Edge_Direction":0},{"Position":{"x":6.0,"y":13.5,"z":0.0},"Edge_Type":2,"Edge_Direction":0},{"Position":{"x":7.0,"y":0.5,"z":0.0},"Edge_Type":2,"Edge_Direction":0},{"Position":{"x":7.0,"y":1.5,"z":0.0},"Edge_Type":0,"Edge_Direction":0},{"Position":{"x":7.0,"y":2.5,"z":0.0},"Edge_Type":0,"Edge_Direction":0},{"Position":{"x":7.0,"y":3.5,"z":0.0},"Edge_Type":2,"Edge_Direction":0},{"Position":{"x":7.0,"y":4.5,"z":0.0},"Edge_Type":0,"Edge_Direction":0},{"Position":{"x":7.0,"y":5.5,"z":0.0},"Edge_Type":2,"Edge_Direction":0},{"Position":{"x":7.0,"y":6.5,"z":0.0},"Edge_Type":2,"Edge_Direction":0},{"Position":{"x":7.0,"y":7.5,"z":0.0},"Edge_Type":2,"Edge_Direction":0},{"Position":{"x":7.0,"y":8.5,"z":0.0},"Edge_Type":2,"Edge_Direction":0},{"Position":{"x":7.0,"y":9.5,"z":0.0},"Edge_Type":0,"Edge_Direction":0},{"Position":{"x":7.0,"y":10.5,"z":0.0},"Edge_Type":2,"Edge_Direction":0},{"Position":{"x":7.0,"y":11.5,"z":0.0},"Edge_Type":0,"Edge_Direction":0},{"Position":{"x":7.0,"y":12.5,"z":0.0},"Edge_Type":0,"Edge_Direction":0},{"Position":{"x":7.0,"y":13.5,"z":0.0},"Edge_Type":2,"Edge_Direction":0},{"Position":{"x":8.0,"y":0.5,"z":0.0},"Edge_Type":2,"Edge_Direction":0},{"Position":{"x":8.0,"y":1.5,"z":0.0},"Edge_Type":2,"Edge_Direction":0},{"Position":{"x":8.0,"y":2.5,"z":0.0},"Edge_Type":2,"Edge_Direction":0},{"Position":{"x":8.0,"y":3.5,"z":0.0},"Edge_Type":2,"Edge_Direction":0},{"Position":{"x":8.0,"y":4.5,"z":0.0},"Edge_Type":0,"Edge_Direction":0},{"Position":{"x":8.0,"y":5.5,"z":0.0},"Edge_Type":2,"Edge_Direction":0},{"Position":{"x":8.0,"y":6.5,"z":0.0},"Edge_Type":0,"Edge_Direction":0},{"Position":{"x":8.0,"y":7.5,"z":0.0},"Edge_Type":2,"Edge_Direction":0},{"Position":{"x":8.0,"y":8.5,"z":0.0},"Edge_Type":2,"Edge_Direction":0},{"Position":{"x":8.0,"y":9.5,"z":0.0},"Edge_Type":0,"Edge_Direction":0},{"Position":{"x":8.0,"y":10.5,"z":0.0},"Edge_Type":2,"Edge_Direction":0},{"Position":{"x":8.0,"y":11.5,"z":0.0},"Edge_Type":2,"Edge_Direction":0},{"Position":{"x":8.0,"y":12.5,"z":0.0},"Edge_Type":2,"Edge_Direction":0},{"Position":{"x":8.0,"y":13.5,"z":0.0},"Edge_Type":2,"Edge_Direction":0},{"Position":{"x":9.0,"y":0.5,"z":0.0},"Edge_Type":2,"Edge_Direction":0},{"Position":{"x":9.0,"y":1.5,"z":0.0},"Edge_Type":2,"Edge_Direction":0},{"Position":{"x":9.0,"y":2.5,"z":0.0},"Edge_Type":2,"Edge_Direction":0},{"Position":{"x":9.0,"y":3.5,"z":0.0},"Edge_Type":2,"Edge_Direction":0},{"Position":{"x":9.0,"y":4.5,"z":0.0},"Edge_Type":0,"Edge_Direction":0},{"Position":{"x":9.0,"y":5.5,"z":0.0},"Edge_Type":0,"Edge_Direction":0},{"Position":{"x":9.0,"y":6.5,"z":0.0},"Edge_Type":2,"Edge_Direction":0},{"Position":{"x":9.0,"y":7.5,"z":0.0},"Edge_Type":0,"Edge_Direction":0},{"Position":{"x":9.0,"y":8.5,"z":0.0},"Edge_Type":2,"Edge_Direction":0},{"Position":{"x":9.0,"y":9.5,"z":0.0},"Edge_Type":0,"Edge_Direction":0},{"Position":{"x":9.0,"y":10.5,"z":0.0},"Edge_Type":2,"Edge_Direction":0},{"Position":{"x":9.0,"y":11.5,"z":0.0},"Edge_Type":2,"Edge_Direction":0},{"Position":{"x":9.0,"y":12.5,"z":0.0},"Edge_Type":2,"Edge_Direction":0},{"Position":{"x":9.0,"y":13.5,"z":0.0},"Edge_Type":2,"Edge_Direction":0},{"Position":{"x":10.0,"y":0.5,"z":0.0},"Edge_Type":2,"Edge_Direction":0},{"Position":{"x":10.0,"y":1.5,"z":0.0},"Edge_Type":2,"Edge_Direction":0},{"Position":{"x":10.0,"y":2.5,"z":0.0},"Edge_Type":2,"Edge_Direction":0},{"Position":{"x":10.0,"y":3.5,"z":0.0},"Edge_Type":2,"Edge_Direction":0},{"Position":{"x":10.0,"y":4.5,"z":0.0},"Edge_Type":0,"Edge_Direction":0},{"Position":{"x":10.0,"y":5.5,"z":0.0},"Edge_Type":0,"Edge_Direction":0},{"Position":{"x":10.0,"y":6.5,"z":0.0},"Edge_Type":2,"Edge_Direction":0},{"Position":{"x":10.0,"y":7.5,"z":0.0},"Edge_Type":2,"Edge_Direction":0},{"Position":{"x":10.0,"y":8.5,"z":0.0},"Edge_Type":0,"Edge_Direction":0},{"Position":{"x":10.0,"y":9.5,"z":0.0},"Edge_Type":0,"Edge_Direction":0},{"Position":{"x":10.0,"y":10.5,"z":0.0},"Edge_Type":2,"Edge_Direction":0},{"Position":{"x":10.0,"y":11.5,"z":0.0},"Edge_Type":2,"Edge_Direction":0},{"Position":{"x":10.0,"y":12.5,"z":0.0},"Edge_Type":2,"Edge_Direction":0},{"Position":{"x":10.0,"y":13.5,"z":0.0},"Edge_Type":2,"Edge_Direction":0},{"Position":{"x":11.0,"y":0.5,"z":0.0},"Edge_Type":2,"Edge_Direction":0},{"Position":{"x":11.0,"y":1.5,"z":0.0},"Edge_Type":2,"Edge_Direction":0},{"Position":{"x":11.0,"y":2.5,"z":0.0},"Edge_Type":2,"Edge_Direction":0},{"Position":{"x":11.0,"y":3.5,"z":0.0},"Edge_Type":0,"Edge_Direction":0},{"Position":{"x":11.0,"y":4.5,"z":0.0},"Edge_Type":0,"Edge_Direction":0},{"Position":{"x":11.0,"y":5.5,"z":0.0},"Edge_Type":0,"Edge_Direction":0},{"Position":{"x":11.0,"y":6.5,"z":0.0},"Edge_Type":0,"Edge_Direction":0},{"Position":{"x":11.0,"y":7.5,"z":0.0},"Edge_Type":0,"Edge_Direction":0},{"Position":{"x":11.0,"y":8.5,"z":0.0},"Edge_Type":0,"Edge_Direction":0},{"Position":{"x":11.0,"y":9.5,"z":0.0},"Edge_Type":0,"Edge_Direction":0},{"Position":{"x":11.0,"y":10.5,"z":0.0},"Edge_Type":0,"Edge_Direction":0},{"Position":{"x":11.0,"y":11.5,"z":0.0},"Edge_Type":2,"Edge_Direction":0},{"Position":{"x":11.0,"y":12.5,"z":0.0},"Edge_Type":2,"Edge_Direction":0},{"Position":{"x":11.0,"y":13.5,"z":0.0},"Edge_Type":2,"Edge_Direction":0},{"Position":{"x":12.0,"y":0.5,"z":0.0},"Edge_Type":2,"Edge_Direction":0},{"Position":{"x":12.0,"y":1.5,"z":0.0},"Edge_Type":2,"Edge_Direction":0},{"Position":{"x":12.0,"y":2.5,"z":0.0},"Edge_Type":0,"Edge_Direction":0},{"Position":{"x":12.0,"y":3.5,"z":0.0},"Edge_Type":0,"Edge_Direction":0},{"Position":{"x":12.0,"y":4.5,"z":0.0},"Edge_Type":0,"Edge_Direction":0},{"Position":{"x":12.0,"y":5.5,"z":0.0},"Edge_Type":0,"Edge_Direction":0},{"Position":{"x":12.0,"y":6.5,"z":0.0},"Edge_Type":0,"Edge_Direction":0},{"Position":{"x":12.0,"y":7.5,"z":0.0},"Edge_Type":0,"Edge_Direction":0},{"Position":{"x":12.0,"y":8.5,"z":0.0},"Edge_Type":0,"Edge_Direction":0},{"Position":{"x":12.0,"y":9.5,"z":0.0},"Edge_Type":0,"Edge_Direction":0},{"Position":{"x":12.0,"y":10.5,"z":0.0},"Edge_Type":0,"Edge_Direction":0},{"Position":{"x":12.0,"y":11.5,"z":0.0},"Edge_Type":0,"Edge_Direction":0},{"Position":{"x":12.0,"y":12.5,"z":0.0},"Edge_Type":2,"Edge_Direction":0},{"Position":{"x":12.0,"y":13.5,"z":0.0},"Edge_Type":2,"Edge_Direction":0},{"Position":{"x":13.0,"y":0.5,"z":0.0},"Edge_Type":2,"Edge_Direction":0},{"Position":{"x":13.0,"y":1.5,"z":0.0},"Edge_Type":0,"Edge_Direction":0},{"Position":{"x":13.0,"y":2.5,"z":0.0},"Edge_Type":0,"Edge_Direction":0},{"Position":{"x":13.0,"y":3.5,"z":0.0},"Edge_Type":0,"Edge_Direction":0},{"Position":{"x":13.0,"y":4.5,"z":0.0},"Edge_Type":0,"Edge_Direction":0},{"Position":{"x":13.0,"y":5.5,"z":0.0},"Edge_Type":0,"Edge_Direction":0},{"Position":{"x":13.0,"y":6.5,"z":0.0},"Edge_Type":0,"Edge_Direction":0},{"Position":{"x":13.0,"y":7.5,"z":0.0},"Edge_Type":0,"Edge_Direction":0},{"Position":{"x":13.0,"y":8.5,"z":0.0},"Edge_Type":0,"Edge_Direction":0},{"Position":{"x":13.0,"y":9.5,"z":0.0},"Edge_Type":0,"Edge_Direction":0},{"Position":{"x":13.0,"y":10.5,"z":0.0},"Edge_Type":0,"Edge_Direction":0},{"Position":{"x":13.0,"y":11.5,"z":0.0},"Edge_Type":0,"Edge_Direction":0},{"Position":{"x":13.0,"y":12.5,"z":0.0},"Edge_Type":0,"Edge_Direction":0},{"Position":{"x":13.0,"y":13.5,"z":0.0},"Edge_Type":2,"Edge_Direction":0},{"Position":{"x":14.0,"y":0.5,"z":0.0},"Edge_Type":0,"Edge_Direction":0},{"Position":{"x":14.0,"y":1.5,"z":0.0},"Edge_Type":0,"Edge_Direction":0},{"Position":{"x":14.0,"y":2.5,"z":0.0},"Edge_Type":0,"Edge_Direction":0},{"Position":{"x":14.0,"y":3.5,"z":0.0},"Edge_Type":0,"Edge_Direction":0},{"Position":{"x":14.0,"y":4.5,"z":0.0},"Edge_Type":0,"Edge_Direction":0},{"Position":{"x":14.0,"y":5.5,"z":0.0},"Edge_Type":0,"Edge_Direction":0},{"Position":{"x":14.0,"y":6.5,"z":0.0},"Edge_Type":0,"Edge_Direction":0},{"Position":{"x":14.0,"y":7.5,"z":0.0},"Edge_Type":0,"Edge_Direction":0},{"Position":{"x":14.0,"y":8.5,"z":0.0},"Edge_Type":0,"Edge_Direction":0},{"Position":{"x":14.0,"y":9.5,"z":0.0},"Edge_Type":0,"Edge_Direction":0},{"Position":{"x":14.0,"y":10.5,"z":0.0},"Edge_Type":0,"Edge_Direction":0},{"Position":{"x":14.0,"y":11.5,"z":0.0},"Edge_Type":0,"Edge_Direction":0},{"Position":{"x":14.0,"y":12.5,"z":0.0},"Edge_Type":0,"Edge_Direction":0},{"Position":{"x":14.0,"y":13.5,"z":0.0},"Edge_Type":0,"Edge_Direction":0}],"BL_V_Edges":[{"Position":{"x":0.5,"y":0.0,"z":0.0},"Edge_Type":0,"Edge_Direction":1},{"Position":{"x":0.5,"y":1.0,"z":0.0},"Edge_Type":2,"Edge_Direction":1},{"Position":{"x":0.5,"y":2.0,"z":0.0},"Edge_Type":2,"Edge_Direction":1},{"Position":{"x":0.5,"y":3.0,"z":0.0},"Edge_Type":2,"Edge_Direction":1},{"Position":{"x":0.5,"y":4.0,"z":0.0},"Edge_Type":2,"Edge_Direction":1},{"Position":{"x":0.5,"y":5.0,"z":0.0},"Edge_Type":2,"Edge_Direction":1},{"Position":{"x":0.5,"y":6.0,"z":0.0},"Edge_Type":2,"Edge_Direction":1},{"Position":{"x":0.5,"y":7.0,"z":0.0},"Edge_Type":2,"Edge_Direction":1},{"Position":{"x":0.5,"y":8.0,"z":0.0},"Edge_Type":2,"Edge_Direction":1},{"Position":{"x":0.5,"y":9.0,"z":0.0},"Edge_Type":2,"Edge_Direction":1},{"Position":{"x":0.5,"y":10.0,"z":0.0},"Edge_Type":2,"Edge_Direction":1},{"Position":{"x":0.5,"y":11.0,"z":0.0},"Edge_Type":2,"Edge_Direction":1},{"Position":{"x":0.5,"y":12.0,"z":0.0},"Edge_Type":2,"Edge_Direction":1},{"Position":{"x":0.5,"y":13.0,"z":0.0},"Edge_Type":2,"Edge_Direction":1},{"Position":{"x":0.5,"y":14.0,"z":0.0},"Edge_Type":0,"Edge_Direction":1},{"Position":{"x":1.5,"y":0.0,"z":0.0},"Edge_Type":0,"Edge_Direction":1},{"Position":{"x":1.5,"y":1.0,"z":0.0},"Edge_Type":0,"Edge_Direction":1},{"Position":{"x":1.5,"y":2.0,"z":0.0},"Edge_Type":2,"Edge_Direction":1},{"Position":{"x":1.5,"y":3.0,"z":0.0},"Edge_Type":2,"Edge_Direction":1},{"Position":{"x":1.5,"y":4.0,"z":0.0},"Edge_Type":2,"Edge_Direction":1},{"Position":{"x":1.5,"y":5.0,"z":0.0},"Edge_Type":2,"Edge_Direction":1},{"Position":{"x":1.5,"y":6.0,"z":0.0},"Edge_Type":2,"Edge_Direction":1},{"Position":{"x":1.5,"y":7.0,"z":0.0},"Edge_Type":2,"Edge_Direction":1},{"Position":{"x":1.5,"y":8.0,"z":0.0},"Edge_Type":2,"Edge_Direction":1},{"Position":{"x":1.5,"y":9.0,"z":0.0},"Edge_Type":2,"Edge_Direction":1},{"Position":{"x":1.5,"y":10.0,"z":0.0},"Edge_Type":2,"Edge_Direction":1},{"Position":{"x":1.5,"y":11.0,"z":0.0},"Edge_Type":2,"Edge_Direction":1},{"Position":{"x":1.5,"y":12.0,"z":0.0},"Edge_Type":2,"Edge_Direction":1},{"Position":{"x":1.5,"y":13.0,"z":0.0},"Edge_Type":0,"Edge_Direction":1},{"Position":{"x":1.5,"y":14.0,"z":0.0},"Edge_Type":0,"Edge_Direction":1},{"Position":{"x":2.5,"y":0.0,"z":0.0},"Edge_Type":0,"Edge_Direction":1},{"Position":{"x":2.5,"y":1.0,"z":0.0},"Edge_Type":0,"Edge_Direction":1},{"Position":{"x":2.5,"y":2.0,"z":0.0},"Edge_Type":0,"Edge_Direction":1},{"Position":{"x":2.5,"y":3.0,"z":0.0},"Edge_Type":2,"Edge_Direction":1},{"Position":{"x":2.5,"y":4.0,"z":0.0},"Edge_Type":2,"Edge_Direction":1},{"Position":{"x":2.5,"y":5.0,"z":0.0},"Edge_Type":2,"Edge_Direction":1},{"Position":{"x":2.5,"y":6.0,"z":0.0},"Edge_Type":2,"Edge_Direction":1},{"Position":{"x":2.5,"y":7.0,"z":0.0},"Edge_Type":2,"Edge_Direction":1},{"Position":{"x":2.5,"y":8.0,"z":0.0},"Edge_Type":2,"Edge_Direction":1},{"Position":{"x":2.5,"y":9.0,"z":0.0},"Edge_Type":2,"Edge_Direction":1},{"Position":{"x":2.5,"y":10.0,"z":0.0},"Edge_Type":2,"Edge_Direction":1},{"Position":{"x":2.5,"y":11.0,"z":0.0},"Edge_Type":2,"Edge_Direction":1},{"Position":{"x":2.5,"y":12.0,"z":0.0},"Edge_Type":0,"Edge_Direction":1},{"Position":{"x":2.5,"y":13.0,"z":0.0},"Edge_Type":0,"Edge_Direction":1},{"Position":{"x":2.5,"y":14.0,"z":0.0},"Edge_Type":0,"Edge_Direction":1},{"Position":{"x":3.5,"y":0.0,"z":0.0},"Edge_Type":0,"Edge_Direction":1},{"Position":{"x":3.5,"y":1.0,"z":0.0},"Edge_Type":0,"Edge_Direction":1},{"Position":{"x":3.5,"y":2.0,"z":0.0},"Edge_Type":0,"Edge_Direction":1},{"Position":{"x":3.5,"y":3.0,"z":0.0},"Edge_Type":0,"Edge_Direction":1},{"Position":{"x":3.5,"y":4.0,"z":0.0},"Edge_Type":2,"Edge_Direction":1},{"Position":{"x":3.5,"y":5.0,"z":0.0},"Edge_Type":2,"Edge_Direction":1},{"Position":{"x":3.5,"y":6.0,"z":0.0},"Edge_Type":2,"Edge_Direction":1},{"Position":{"x":3.5,"y":7.0,"z":0.0},"Edge_Type":0,"Edge_Direction":1},{"Position":{"x":3.5,"y":8.0,"z":0.0},"Edge_Type":2,"Edge_Direction":1},{"Position":{"x":3.5,"y":9.0,"z":0.0},"Edge_Type":2,"Edge_Direction":1},{"Position":{"x":3.5,"y":10.0,"z":0.0},"Edge_Type":2,"Edge_Direction":1},{"Position":{"x":3.5,"y":11.0,"z":0.0},"Edge_Type":0,"Edge_Direction":1},{"Position":{"x":3.5,"y":12.0,"z":0.0},"Edge_Type":0,"Edge_Direction":1},{"Position":{"x":3.5,"y":13.0,"z":0.0},"Edge_Type":0,"Edge_Direction":1},{"Position":{"x":3.5,"y":14.0,"z":0.0},"Edge_Type":0,"Edge_Direction":1},{"Position":{"x":4.5,"y":0.0,"z":0.0},"Edge_Type":0,"Edge_Direction":1},{"Position":{"x":4.5,"y":1.0,"z":0.0},"Edge_Type":0,"Edge_Direction":1},{"Position":{"x":4.5,"y":2.0,"z":0.0},"Edge_Type":0,"Edge_Direction":1},{"Position":{"x":4.5,"y":3.0,"z":0.0},"Edge_Type":0,"Edge_Direction":1},{"Position":{"x":4.5,"y":4.0,"z":0.0},"Edge_Type":0,"Edge_Direction":1},{"Position":{"x":4.5,"y":5.0,"z":0.0},"Edge_Type":0,"Edge_Direction":1},{"Position":{"x":4.5,"y":6.0,"z":0.0},"Edge_Type":2,"Edge_Direction":1},{"Position":{"x":4.5,"y":7.0,"z":0.0},"Edge_Type":0,"Edge_Direction":1},{"Position":{"x":4.5,"y":8.0,"z":0.0},"Edge_Type":0,"Edge_Direction":1},{"Position":{"x":4.5,"y":9.0,"z":0.0},"Edge_Type":0,"Edge_Direction":1},{"Position":{"x":4.5,"y":10.0,"z":0.0},"Edge_Type":0,"Edge_Direction":1},{"Position":{"x":4.5,"y":11.0,"z":0.0},"Edge_Type":0,"Edge_Direction":1},{"Position":{"x":4.5,"y":12.0,"z":0.0},"Edge_Type":0,"Edge_Direction":1},{"Position":{"x":4.5,"y":13.0,"z":0.0},"Edge_Type":0,"Edge_Direction":1},{"Position":{"x":4.5,"y":14.0,"z":0.0},"Edge_Type":0,"Edge_Direction":1},{"Position":{"x":5.5,"y":0.0,"z":0.0},"Edge_Type":0,"Edge_Direction":1},{"Position":{"x":5.5,"y":1.0,"z":0.0},"Edge_Type":0,"Edge_Direction":1},{"Position":{"x":5.5,"y":2.0,"z":0.0},"Edge_Type":0,"Edge_Direction":1},{"Position":{"x":5.5,"y":3.0,"z":0.0},"Edge_Type":0,"Edge_Direction":1},{"Position":{"x":5.5,"y":4.0,"z":0.0},"Edge_Type":0,"Edge_Direction":1},{"Position":{"x":5.5,"y":5.0,"z":0.0},"Edge_Type":0,"Edge_Direction":1},{"Position":{"x":5.5,"y":6.0,"z":0.0},"Edge_Type":0,"Edge_Direction":1},{"Position":{"x":5.5,"y":7.0,"z":0.0},"Edge_Type":2,"Edge_Direction":1},{"Position":{"x":5.5,"y":8.0,"z":0.0},"Edge_Type":2,"Edge_Direction":1},{"Position":{"x":5.5,"y":9.0,"z":0.0},"Edge_Type":0,"Edge_Direction":1},{"Position":{"x":5.5,"y":10.0,"z":0.0},"Edge_Type":0,"Edge_Direction":1},{"Position":{"x":5.5,"y":11.0,"z":0.0},"Edge_Type":0,"Edge_Direction":1},{"Position":{"x":5.5,"y":12.0,"z":0.0},"Edge_Type":0,"Edge_Direction":1},{"Position":{"x":5.5,"y":13.0,"z":0.0},"Edge_Type":0,"Edge_Direction":1},{"Position":{"x":5.5,"y":14.0,"z":0.0},"Edge_Type":0,"Edge_Direction":1},{"Position":{"x":6.5,"y":0.0,"z":0.0},"Edge_Type":0,"Edge_Direction":1},{"Position":{"x":6.5,"y":1.0,"z":0.0},"Edge_Type":0,"Edge_Direction":1},{"Position":{"x":6.5,"y":2.0,"z":0.0},"Edge_Type":2,"Edge_Direction":1},{"Position":{"x":6.5,"y":3.0,"z":0.0},"Edge_Type":0,"Edge_Direction":1},{"Position":{"x":6.5,"y":4.0,"z":0.0},"Edge_Type":0,"Edge_Direction":1},{"Position":{"x":6.5,"y":5.0,"z":0.0},"Edge_Type":0,"Edge_Direction":1},{"Position":{"x":6.5,"y":6.0,"z":0.0},"Edge_Type":0,"Edge_Direction":1},{"Position":{"x":6.5,"y":7.0,"z":0.0},"Edge_Type":2,"Edge_Direction":1},{"Position":{"x":6.5,"y":8.0,"z":0.0},"Edge_Type":0,"Edge_Direction":1},{"Position":{"x":6.5,"y":9.0,"z":0.0},"Edge_Type":0,"Edge_Direction":1},{"Position":{"x":6.5,"y":10.0,"z":0.0},"Edge_Type":0,"Edge_Direction":1},{"Position":{"x":6.5,"y":11.0,"z":0.0},"Edge_Type":0,"Edge_Direction":1},{"Position":{"x":6.5,"y":12.0,"z":0.0},"Edge_Type":2,"Edge_Direction":1},{"Position":{"x":6.5,"y":13.0,"z":0.0},"Edge_Type":0,"Edge_Direction":1},{"Position":{"x":6.5,"y":14.0,"z":0.0},"Edge_Type":0,"Edge_Direction":1},{"Position":{"x":7.5,"y":0.0,"z":0.0},"Edge_Type":0,"Edge_Direction":1},{"Position":{"x":7.5,"y":1.0,"z":0.0},"Edge_Type":0,"Edge_Direction":1},{"Position":{"x":7.5,"y":2.0,"z":0.0},"Edge_Type":2,"Edge_Direction":1},{"Position":{"x":7.5,"y":3.0,"z":0.0},"Edge_Type":0,"Edge_Direction":1},{"Position":{"x":7.5,"y":4.0,"z":0.0},"Edge_Type":0,"Edge_Direction":1},{"Position":{"x":7.5,"y":5.0,"z":0.0},"Edge_Type":0,"Edge_Direction":1},{"Position":{"x":7.5,"y":6.0,"z":0.0},"Edge_Type":0,"Edge_Direction":1},{"Position":{"x":7.5,"y":7.0,"z":0.0},"Edge_Type":2,"Edge_Direction":1},{"Position":{"x":7.5,"y":8.0,"z":0.0},"Edge_Type":0,"Edge_Direction":1},{"Position":{"x":7.5,"y":9.0,"z":0.0},"Edge_Type":0,"Edge_Direction":1},{"Position":{"x":7.5,"y":10.0,"z":0.0},"Edge_Type":0,"Edge_Direction":1},{"Position":{"x":7.5,"y":11.0,"z":0.0},"Edge_Type":0,"Edge_Direction":1},{"Position":{"x":7.5,"y":12.0,"z":0.0},"Edge_Type":2,"Edge_Direction":1},{"Position":{"x":7.5,"y":13.0,"z":0.0},"Edge_Type":0,"Edge_Direction":1},{"Position":{"x":7.5,"y":14.0,"z":0.0},"Edge_Type":0,"Edge_Direction":1},{"Position":{"x":8.5,"y":0.0,"z":0.0},"Edge_Type":0,"Edge_Direction":1},{"Position":{"x":8.5,"y":1.0,"z":0.0},"Edge_Type":0,"Edge_Direction":1},{"Position":{"x":8.5,"y":2.0,"z":0.0},"Edge_Type":0,"Edge_Direction":1},{"Position":{"x":8.5,"y":3.0,"z":0.0},"Edge_Type":0,"Edge_Direction":1},{"Position":{"x":8.5,"y":4.0,"z":0.0},"Edge_Type":0,"Edge_Direction":1},{"Position":{"x":8.5,"y":5.0,"z":0.0},"Edge_Type":0,"Edge_Direction":1},{"Position":{"x":8.5,"y":6.0,"z":0.0},"Edge_Type":2,"Edge_Direction":1},{"Position":{"x":8.5,"y":7.0,"z":0.0},"Edge_Type":2,"Edge_Direction":1},{"Position":{"x":8.5,"y":8.0,"z":0.0},"Edge_Type":0,"Edge_Direction":1},{"Position":{"x":8.5,"y":9.0,"z":0.0},"Edge_Type":0,"Edge_Direction":1},{"Position":{"x":8.5,"y":10.0,"z":0.0},"Edge_Type":0,"Edge_Direction":1},{"Position":{"x":8.5,"y":11.0,"z":0.0},"Edge_Type":0,"Edge_Direction":1},{"Position":{"x":8.5,"y":12.0,"z":0.0},"Edge_Type":0,"Edge_Direction":1},{"Position":{"x":8.5,"y":13.0,"z":0.0},"Edge_Type":0,"Edge_Direction":1},{"Position":{"x":8.5,"y":14.0,"z":0.0},"Edge_Type":0,"Edge_Direction":1},{"Position":{"x":9.5,"y":0.0,"z":0.0},"Edge_Type":0,"Edge_Direction":1},{"Position":{"x":9.5,"y":1.0,"z":0.0},"Edge_Type":0,"Edge_Direction":1},{"Position":{"x":9.5,"y":2.0,"z":0.0},"Edge_Type":0,"Edge_Direction":1},{"Position":{"x":9.5,"y":3.0,"z":0.0},"Edge_Type":0,"Edge_Direction":1},{"Position":{"x":9.5,"y":4.0,"z":0.0},"Edge_Type":0,"Edge_Direction":1},{"Position":{"x":9.5,"y":5.0,"z":0.0},"Edge_Type":0,"Edge_Direction":1},{"Position":{"x":9.5,"y":6.0,"z":0.0},"Edge_Type":0,"Edge_Direction":1},{"Position":{"x":9.5,"y":7.0,"z":0.0},"Edge_Type":0,"Edge_Direction":1},{"Position":{"x":9.5,"y":8.0,"z":0.0},"Edge_Type":2,"Edge_Direction":1},{"Position":{"x":9.5,"y":9.0,"z":0.0},"Edge_Type":0,"Edge_Direction":1},{"Position":{"x":9.5,"y":10.0,"z":0.0},"Edge_Type":0,"Edge_Direction":1},{"Position":{"x":9.5,"y":11.0,"z":0.0},"Edge_Type":0,"Edge_Direction":1},{"Position":{"x":9.5,"y":12.0,"z":0.0},"Edge_Type":0,"Edge_Direction":1},{"Position":{"x":9.5,"y":13.0,"z":0.0},"Edge_Type":0,"Edge_Direction":1},{"Position":{"x":9.5,"y":14.0,"z":0.0},"Edge_Type":0,"Edge_Direction":1},{"Position":{"x":10.5,"y":0.0,"z":0.0},"Edge_Type":0,"Edge_Direction":1},{"Position":{"x":10.5,"y":1.0,"z":0.0},"Edge_Type":0,"Edge_Direction":1},{"Position":{"x":10.5,"y":2.0,"z":0.0},"Edge_Type":0,"Edge_Direction":1},{"Position":{"x":10.5,"y":3.0,"z":0.0},"Edge_Type":0,"Edge_Direction":1},{"Position":{"x":10.5,"y":4.0,"z":0.0},"Edge_Type":2,"Edge_Direction":1},{"Position":{"x":10.5,"y":5.0,"z":0.0},"Edge_Type":2,"Edge_Direction":1},{"Position":{"x":10.5,"y":6.0,"z":0.0},"Edge_Type":2,"Edge_Direction":1},{"Position":{"x":10.5,"y":7.0,"z":0.0},"Edge_Type":0,"Edge_Direction":1},{"Position":{"x":10.5,"y":8.0,"z":0.0},"Edge_Type":2,"Edge_Direction":1},{"Position":{"x":10.5,"y":9.0,"z":0.0},"Edge_Type":2,"Edge_Direction":1},{"Position":{"x":10.5,"y":10.0,"z":0.0},"Edge_Type":2,"Edge_Direction":1},{"Position":{"x":10.5,"y":11.0,"z":0.0},"Edge_Type":0,"Edge_Direction":1},{"Position":{"x":10.5,"y":12.0,"z":0.0},"Edge_Type":0,"Edge_Direction":1},{"Position":{"x":10.5,"y":13.0,"z":0.0},"Edge_Type":0,"Edge_Direction":1},{"Position":{"x":10.5,"y":14.0,"z":0.0},"Edge_Type":0,"Edge_Direction":1},{"Position":{"x":11.5,"y":0.0,"z":0.0},"Edge_Type":0,"Edge_Direction":1},{"Position":{"x":11.5,"y":1.0,"z":0.0},"Edge_Type":0,"Edge_Direction":1},{"Position":{"x":11.5,"y":2.0,"z":0.0},"Edge_Type":0,"Edge_Direction":1},{"Position":{"x":11.5,"y":3.0,"z":0.0},"Edge_Type":2,"Edge_Direction":1},{"Position":{"x":11.5,"y":4.0,"z":0.0},"Edge_Type":2,"Edge_Direction":1},{"Position":{"x":11.5,"y":5.0,"z":0.0},"Edge_Type":2,"Edge_Direction":1},{"Position":{"x":11.5,"y":6.0,"z":0.0},"Edge_Type":2,"Edge_Direction":1},{"Position":{"x":11.5,"y":7.0,"z":0.0},"Edge_Type":2,"Edge_Direction":1},{"Position":{"x":11.5,"y":8.0,"z":0.0},"Edge_Type":2,"Edge_Direction":1},{"Position":{"x":11.5,"y":9.0,"z":0.0},"Edge_Type":2,"Edge_Direction":1},{"Position":{"x":11.5,"y":10.0,"z":0.0},"Edge_Type":2,"Edge_Direction":1},{"Position":{"x":11.5,"y":11.0,"z":0.0},"Edge_Type":2,"Edge_Direction":1},{"Position":{"x":11.5,"y":12.0,"z":0.0},"Edge_Type":0,"Edge_Direction":1},{"Position":{"x":11.5,"y":13.0,"z":0.0},"Edge_Type":0,"Edge_Direction":1},{"Position":{"x":11.5,"y":14.0,"z":0.0},"Edge_Type":0,"Edge_Direction":1},{"Position":{"x":12.5,"y":0.0,"z":0.0},"Edge_Type":0,"Edge_Direction":1},{"Position":{"x":12.5,"y":1.0,"z":0.0},"Edge_Type":0,"Edge_Direction":1},{"Position":{"x":12.5,"y":2.0,"z":0.0},"Edge_Type":2,"Edge_Direction":1},{"Position":{"x":12.5,"y":3.0,"z":0.0},"Edge_Type":2,"Edge_Direction":1},{"Position":{"x":12.5,"y":4.0,"z":0.0},"Edge_Type":2,"Edge_Direction":1},{"Position":{"x":12.5,"y":5.0,"z":0.0},"Edge_Type":2,"Edge_Direction":1},{"Position":{"x":12.5,"y":6.0,"z":0.0},"Edge_Type":2,"Edge_Direction":1},{"Position":{"x":12.5,"y":7.0,"z":0.0},"Edge_Type":2,"Edge_Direction":1},{"Position":{"x":12.5,"y":8.0,"z":0.0},"Edge_Type":2,"Edge_Direction":1},{"Position":{"x":12.5,"y":9.0,"z":0.0},"Edge_Type":2,"Edge_Direction":1},{"Position":{"x":12.5,"y":10.0,"z":0.0},"Edge_Type":2,"Edge_Direction":1},{"Position":{"x":12.5,"y":11.0,"z":0.0},"Edge_Type":2,"Edge_Direction":1},{"Position":{"x":12.5,"y":12.0,"z":0.0},"Edge_Type":2,"Edge_Direction":1},{"Position":{"x":12.5,"y":13.0,"z":0.0},"Edge_Type":0,"Edge_Direction":1},{"Position":{"x":12.5,"y":14.0,"z":0.0},"Edge_Type":0,"Edge_Direction":1},{"Position":{"x":13.5,"y":0.0,"z":0.0},"Edge_Type":0,"Edge_Direction":1},{"Position":{"x":13.5,"y":1.0,"z":0.0},"Edge_Type":2,"Edge_Direction":1},{"Position":{"x":13.5,"y":2.0,"z":0.0},"Edge_Type":2,"Edge_Direction":1},{"Position":{"x":13.5,"y":3.0,"z":0.0},"Edge_Type":2,"Edge_Direction":1},{"Position":{"x":13.5,"y":4.0,"z":0.0},"Edge_Type":2,"Edge_Direction":1},{"Position":{"x":13.5,"y":5.0,"z":0.0},"Edge_Type":2,"Edge_Direction":1},{"Position":{"x":13.5,"y":6.0,"z":0.0},"Edge_Type":2,"Edge_Direction":1},{"Position":{"x":13.5,"y":7.0,"z":0.0},"Edge_Type":2,"Edge_Direction":1},{"Position":{"x":13.5,"y":8.0,"z":0.0},"Edge_Type":2,"Edge_Direction":1},{"Position":{"x":13.5,"y":9.0,"z":0.0},"Edge_Type":2,"Edge_Direction":1},{"Position":{"x":13.5,"y":10.0,"z":0.0},"Edge_Type":2,"Edge_Direction":1},{"Position":{"x":13.5,"y":11.0,"z":0.0},"Edge_Type":2,"Edge_Direction":1},{"Position":{"x":13.5,"y":12.0,"z":0.0},"Edge_Type":2,"Edge_Direction":1},{"Position":{"x":13.5,"y":13.0,"z":0.0},"Edge_Type":2,"Edge_Direction":1},{"Position":{"x":13.5,"y":14.0,"z":0.0},"Edge_Type":0,"Edge_Direction":1}],"LI_U_Edges":[{"Position":{"x":0.5,"y":0.0,"z":0.0},"Edge_Type":6,"Edge_Direction":0},{"Position":{"x":0.5,"y":1.0,"z":0.0},"Edge_Type":0,"Edge_Direction":0},{"Position":{"x":0.5,"y":2.0,"z":0.0},"Edge_Type":0,"Edge_Direction":0},{"Position":{"x":0.5,"y":3.0,"z":0.0},"Edge_Type":0,"Edge_Direction":0},{"Position":{"x":0.5,"y":4.0,"z":0.0},"Edge_Type":0,"Edge_Direction":0},{"Position":{"x":0.5,"y":5.0,"z":0.0},"Edge_Type":0,"Edge_Direction":0},{"Position":{"x":0.5,"y":6.0,"z":0.0},"Edge_Type":0,"Edge_Direction":0},{"Position":{"x":0.5,"y":7.0,"z":0.0},"Edge_Type":0,"Edge_Direction":0},{"Position":{"x":0.5,"y":8.0,"z":0.0},"Edge_Type":0,"Edge_Direction":0},{"Position":{"x":0.5,"y":9.0,"z":0.0},"Edge_Type":0,"Edge_Direction":0},{"Position":{"x":0.5,"y":10.0,"z":0.0},"Edge_Type":0,"Edge_Direction":0},{"Position":{"x":0.5,"y":11.0,"z":0.0},"Edge_Type":0,"Edge_Direction":0},{"Position":{"x":0.5,"y":12.0,"z":0.0},"Edge_Type":0,"Edge_Direction":0},{"Position":{"x":0.5,"y":13.0,"z":0.0},"Edge_Type":0,"Edge_Direction":0},{"Position":{"x":0.5,"y":14.0,"z":0.0},"Edge_Type":6,"Edge_Direction":0},{"Position":{"x":1.5,"y":0.0,"z":0.0},"Edge_Type":6,"Edge_Direction":0},{"Position":{"x":1.5,"y":1.0,"z":0.0},"Edge_Type":0,"Edge_Direction":0},{"Position":{"x":1.5,"y":2.0,"z":0.0},"Edge_Type":0,"Edge_Direction":0},{"Position":{"x":1.5,"y":3.0,"z":0.0},"Edge_Type":0,"Edge_Direction":0},{"Position":{"x":1.5,"y":4.0,"z":0.0},"Edge_Type":0,"Edge_Direction":0},{"Position":{"x":1.5,"y":5.0,"z":0.0},"Edge_Type":0,"Edge_Direction":0},{"Position":{"x":1.5,"y":6.0,"z":0.0},"Edge_Type":0,"Edge_Direction":0},{"Position":{"x":1.5,"y":7.0,"z":0.0},"Edge_Type":0,"Edge_Direction":0},{"Position":{"x":1.5,"y":8.0,"z":0.0},"Edge_Type":0,"Edge_Direction":0},{"Position":{"x":1.5,"y":9.0,"z":0.0},"Edge_Type":0,"Edge_Direction":0},{"Position":{"x":1.5,"y":10.0,"z":0.0},"Edge_Type":0,"Edge_Direction":0},{"Position":{"x":1.5,"y":11.0,"z":0.0},"Edge_Type":0,"Edge_Direction":0},{"Position":{"x":1.5,"y":12.0,"z":0.0},"Edge_Type":0,"Edge_Direction":0},{"Position":{"x":1.5,"y":13.0,"z":0.0},"Edge_Type":7,"Edge_Direction":0},{"Position":{"x":1.5,"y":14.0,"z":0.0},"Edge_Type":6,"Edge_Direction":0},{"Position":{"x":2.5,"y":0.0,"z":0.0},"Edge_Type":6,"Edge_Direction":0},{"Position":{"x":2.5,"y":1.0,"z":0.0},"Edge_Type":0,"Edge_Direction":0},{"Position":{"x":2.5,"y":2.0,"z":0.0},"Edge_Type":0,"Edge_Direction":0},{"Position":{"x":2.5,"y":3.0,"z":0.0},"Edge_Type":0,"Edge_Direction":0},{"Position":{"x":2.5,"y":4.0,"z":0.0},"Edge_Type":0,"Edge_Direction":0},{"Position":{"x":2.5,"y":5.0,"z":0.0},"Edge_Type":0,"Edge_Direction":0},{"Position":{"x":2.5,"y":6.0,"z":0.0},"Edge_Type":0,"Edge_Direction":0},{"Position":{"x":2.5,"y":7.0,"z":0.0},"Edge_Type":0,"Edge_Direction":0},{"Position":{"x":2.5,"y":8.0,"z":0.0},"Edge_Type":0,"Edge_Direction":0},{"Position":{"x":2.5,"y":9.0,"z":0.0},"Edge_Type":0,"Edge_Direction":0},{"Position":{"x":2.5,"y":10.0,"z":0.0},"Edge_Type":0,"Edge_Direction":0},{"Position":{"x":2.5,"y":11.0,"z":0.0},"Edge_Type":0,"Edge_Direction":0},{"Position":{"x":2.5,"y":12.0,"z":0.0},"Edge_Type":0,"Edge_Direction":0},{"Position":{"x":2.5,"y":13.0,"z":0.0},"Edge_Type":7,"Edge_Direction":0},{"Position":{"x":2.5,"y":14.0,"z":0.0},"Edge_Type":6,"Edge_Direction":0},{"Position":{"x":3.5,"y":0.0,"z":0.0},"Edge_Type":6,"Edge_Direction":0},{"Position":{"x":3.5,"y":1.0,"z":0.0},"Edge_Type":0,"Edge_Direction":0},{"Position":{"x":3.5,"y":2.0,"z":0.0},"Edge_Type":0,"Edge_Direction":0},{"Position":{"x":3.5,"y":3.0,"z":0.0},"Edge_Type":0,"Edge_Direction":0},{"Position":{"x":3.5,"y":4.0,"z":0.0},"Edge_Type":0,"Edge_Direction":0},{"Position":{"x":3.5,"y":5.0,"z":0.0},"Edge_Type":0,"Edge_Direction":0},{"Position":{"x":3.5,"y":6.0,"z":0.0},"Edge_Type":0,"Edge_Direction":0},{"Position":{"x":3.5,"y":7.0,"z":0.0},"Edge_Type":0,"Edge_Direction":0},{"Position":{"x":3.5,"y":8.0,"z":0.0},"Edge_Type":0,"Edge_Direction":0},{"Position":{"x":3.5,"y":9.0,"z":0.0},"Edge_Type":0,"Edge_Direction":0},{"Position":{"x":3.5,"y":10.0,"z":0.0},"Edge_Type":0,"Edge_Direction":0},{"Position":{"x":3.5,"y":11.0,"z":0.0},"Edge_Type":0,"Edge_Direction":0},{"Position":{"x":3.5,"y":12.0,"z":0.0},"Edge_Type":0,"Edge_Direction":0},{"Position":{"x":3.5,"y":13.0,"z":0.0},"Edge_Type":7,"Edge_Direction":0},{"Position":{"x":3.5,"y":14.0,"z":0.0},"Edge_Type":6,"Edge_Direction":0},{"Position":{"x":4.5,"y":0.0,"z":0.0},"Edge_Type":6,"Edge_Direction":0},{"Position":{"x":4.5,"y":1.0,"z":0.0},"Edge_Type":0,"Edge_Direction":0},{"Position":{"x":4.5,"y":2.0,"z":0.0},"Edge_Type":0,"Edge_Direction":0},{"Position":{"x":4.5,"y":3.0,"z":0.0},"Edge_Type":0,"Edge_Direction":0},{"Position":{"x":4.5,"y":4.0,"z":0.0},"Edge_Type":0,"Edge_Direction":0},{"Position":{"x":4.5,"y":5.0,"z":0.0},"Edge_Type":0,"Edge_Direction":0},{"Position":{"x":4.5,"y":6.0,"z":0.0},"Edge_Type":0,"Edge_Direction":0},{"Position":{"x":4.5,"y":7.0,"z":0.0},"Edge_Type":0,"Edge_Direction":0},{"Position":{"x":4.5,"y":8.0,"z":0.0},"Edge_Type":0,"Edge_Direction":0},{"Position":{"x":4.5,"y":9.0,"z":0.0},"Edge_Type":0,"Edge_Direction":0},{"Position":{"x":4.5,"y":10.0,"z":0.0},"Edge_Type":0,"Edge_Direction":0},{"Position":{"x":4.5,"y":11.0,"z":0.0},"Edge_Type":0,"Edge_Direction":0},{"Position":{"x":4.5,"y":12.0,"z":0.0},"Edge_Type":0,"Edge_Direction":0},{"Position":{"x":4.5,"y":13.0,"z":0.0},"Edge_Type":7,"Edge_Direction":0},{"Position":{"x":4.5,"y":14.0,"z":0.0},"Edge_Type":6,"Edge_Direction":0},{"Position":{"x":5.5,"y":0.0,"z":0.0},"Edge_Type":6,"Edge_Direction":0},{"Position":{"x":5.5,"y":1.0,"z":0.0},"Edge_Type":0,"Edge_Direction":0},{"Position":{"x":5.5,"y":2.0,"z":0.0},"Edge_Type":0,"Edge_Direction":0},{"Position":{"x":5.5,"y":3.0,"z":0.0},"Edge_Type":0,"Edge_Direction":0},{"Position":{"x":5.5,"y":4.0,"z":0.0},"Edge_Type":0,"Edge_Direction":0},{"Position":{"x":5.5,"y":5.0,"z":0.0},"Edge_Type":0,"Edge_Direction":0},{"Position":{"x":5.5,"y":6.0,"z":0.0},"Edge_Type":0,"Edge_Direction":0},{"Position":{"x":5.5,"y":7.0,"z":0.0},"Edge_Type":0,"Edge_Direction":0},{"Position":{"x":5.5,"y":8.0,"z":0.0},"Edge_Type":0,"Edge_Direction":0},{"Position":{"x":5.5,"y":9.0,"z":0.0},"Edge_Type":0,"Edge_Direction":0},{"Position":{"x":5.5,"y":10.0,"z":0.0},"Edge_Type":0,"Edge_Direction":0},{"Position":{"x":5.5,"y":11.0,"z":0.0},"Edge_Type":0,"Edge_Direction":0},{"Position":{"x":5.5,"y":12.0,"z":0.0},"Edge_Type":0,"Edge_Direction":0},{"Position":{"x":5.5,"y":13.0,"z":0.0},"Edge_Type":7,"Edge_Direction":0},{"Position":{"x":5.5,"y":14.0,"z":0.0},"Edge_Type":6,"Edge_Direction":0},{"Position":{"x":6.5,"y":0.0,"z":0.0},"Edge_Type":6,"Edge_Direction":0},{"Position":{"x":6.5,"y":1.0,"z":0.0},"Edge_Type":8,"Edge_Direction":0},{"Position":{"x":6.5,"y":2.0,"z":0.0},"Edge_Type":0,"Edge_Direction":0},{"Position":{"x":6.5,"y":3.0,"z":0.0},"Edge_Type":0,"Edge_Direction":0},{"Position":{"x":6.5,"y":4.0,"z":0.0},"Edge_Type":0,"Edge_Direction":0},{"Position":{"x":6.5,"y":5.0,"z":0.0},"Edge_Type":0,"Edge_Direction":0},{"Position":{"x":6.5,"y":6.0,"z":0.0},"Edge_Type":0,"Edge_Direction":0},{"Position":{"x":6.5,"y":7.0,"z":0.0},"Edge_Type":0,"Edge_Direction":0},{"Position":{"x":6.5,"y":8.0,"z":0.0},"Edge_Type":0,"Edge_Direction":0},{"Position":{"x":6.5,"y":9.0,"z":0.0},"Edge_Type":0,"Edge_Direction":0},{"Position":{"x":6.5,"y":10.0,"z":0.0},"Edge_Type":0,"Edge_Direction":0},{"Position":{"x":6.5,"y":11.0,"z":0.0},"Edge_Type":0,"Edge_Direction":0},{"Position":{"x":6.5,"y":12.0,"z":0.0},"Edge_Type":0,"Edge_Direction":0},{"Position":{"x":6.5,"y":13.0,"z":0.0},"Edge_Type":7,"Edge_Direction":0},{"Position":{"x":6.5,"y":14.0,"z":0.0},"Edge_Type":6,"Edge_Direction":0},{"Position":{"x":7.5,"y":0.0,"z":0.0},"Edge_Type":6,"Edge_Direction":0},{"Position":{"x":7.5,"y":1.0,"z":0.0},"Edge_Type":8,"Edge_Direction":0},{"Position":{"x":7.5,"y":2.0,"z":0.0},"Edge_Type":0,"Edge_Direction":0},{"Position":{"x":7.5,"y":3.0,"z":0.0},"Edge_Type":0,"Edge_Direction":0},{"Position":{"x":7.5,"y":4.0,"z":0.0},"Edge_Type":0,"Edge_Direction":0},{"Position":{"x":7.5,"y":5.0,"z":0.0},"Edge_Type":0,"Edge_Direction":0},{"Position":{"x":7.5,"y":6.0,"z":0.0},"Edge_Type":0,"Edge_Direction":0},{"Position":{"x":7.5,"y":7.0,"z":0.0},"Edge_Type":0,"Edge_Direction":0},{"Position":{"x":7.5,"y":8.0,"z":0.0},"Edge_Type":0,"Edge_Direction":0},{"Position":{"x":7.5,"y":9.0,"z":0.0},"Edge_Type":0,"Edge_Direction":0},{"Position":{"x":7.5,"y":10.0,"z":0.0},"Edge_Type":0,"Edge_Direction":0},{"Position":{"x":7.5,"y":11.0,"z":0.0},"Edge_Type":0,"Edge_Direction":0},{"Position":{"x":7.5,"y":12.0,"z":0.0},"Edge_Type":0,"Edge_Direction":0},{"Position":{"x":7.5,"y":13.0,"z":0.0},"Edge_Type":7,"Edge_Direction":0},{"Position":{"x":7.5,"y":14.0,"z":0.0},"Edge_Type":6,"Edge_Direction":0},{"Position":{"x":8.5,"y":0.0,"z":0.0},"Edge_Type":6,"Edge_Direction":0},{"Position":{"x":8.5,"y":1.0,"z":0.0},"Edge_Type":8,"Edge_Direction":0},{"Position":{"x":8.5,"y":2.0,"z":0.0},"Edge_Type":0,"Edge_Direction":0},{"Position":{"x":8.5,"y":3.0,"z":0.0},"Edge_Type":0,"Edge_Direction":0},{"Position":{"x":8.5,"y":4.0,"z":0.0},"Edge_Type":0,"Edge_Direction":0},{"Position":{"x":8.5,"y":5.0,"z":0.0},"Edge_Type":0,"Edge_Direction":0},{"Position":{"x":8.5,"y":6.0,"z":0.0},"Edge_Type":0,"Edge_Direction":0},{"Position":{"x":8.5,"y":7.0,"z":0.0},"Edge_Type":0,"Edge_Direction":0},{"Position":{"x":8.5,"y":8.0,"z":0.0},"Edge_Type":0,"Edge_Direction":0},{"Position":{"x":8.5,"y":9.0,"z":0.0},"Edge_Type":0,"Edge_Direction":0},{"Position":{"x":8.5,"y":10.0,"z":0.0},"Edge_Type":0,"Edge_Direction":0},{"Position":{"x":8.5,"y":11.0,"z":0.0},"Edge_Type":0,"Edge_Direction":0},{"Position":{"x":8.5,"y":12.0,"z":0.0},"Edge_Type":0,"Edge_Direction":0},{"Position":{"x":8.5,"y":13.0,"z":0.0},"Edge_Type":0,"Edge_Direction":0},{"Position":{"x":8.5,"y":14.0,"z":0.0},"Edge_Type":6,"Edge_Direction":0},{"Position":{"x":9.5,"y":0.0,"z":0.0},"Edge_Type":6,"Edge_Direction":0},{"Position":{"x":9.5,"y":1.0,"z":0.0},"Edge_Type":8,"Edge_Direction":0},{"Position":{"x":9.5,"y":2.0,"z":0.0},"Edge_Type":0,"Edge_Direction":0},{"Position":{"x":9.5,"y":3.0,"z":0.0},"Edge_Type":0,"Edge_Direction":0},{"Position":{"x":9.5,"y":4.0,"z":0.0},"Edge_Type":0,"Edge_Direction":0},{"Position":{"x":9.5,"y":5.0,"z":0.0},"Edge_Type":0,"Edge_Direction":0},{"Position":{"x":9.5,"y":6.0,"z":0.0},"Edge_Type":0,"Edge_Direction":0},{"Position":{"x":9.5,"y":7.0,"z":0.0},"Edge_Type":0,"Edge_Direction":0},{"Position":{"x":9.5,"y":8.0,"z":0.0},"Edge_Type":0,"Edge_Direction":0},{"Position":{"x":9.5,"y":9.0,"z":0.0},"Edge_Type":0,"Edge_Direction":0},{"Position":{"x":9.5,"y":10.0,"z":0.0},"Edge_Type":0,"Edge_Direction":0},{"Position":{"x":9.5,"y":11.0,"z":0.0},"Edge_Type":0,"Edge_Direction":0},{"Position":{"x":9.5,"y":12.0,"z":0.0},"Edge_Type":0,"Edge_Direction":0},{"Position":{"x":9.5,"y":13.0,"z":0.0},"Edge_Type":0,"Edge_Direction":0},{"Position":{"x":9.5,"y":14.0,"z":0.0},"Edge_Type":6,"Edge_Direction":0},{"Position":{"x":10.5,"y":0.0,"z":0.0},"Edge_Type":6,"Edge_Direction":0},{"Position":{"x":10.5,"y":1.0,"z":0.0},"Edge_Type":8,"Edge_Direction":0},{"Position":{"x":10.5,"y":2.0,"z":0.0},"Edge_Type":0,"Edge_Direction":0},{"Position":{"x":10.5,"y":3.0,"z":0.0},"Edge_Type":0,"Edge_Direction":0},{"Position":{"x":10.5,"y":4.0,"z":0.0},"Edge_Type":0,"Edge_Direction":0},{"Position":{"x":10.5,"y":5.0,"z":0.0},"Edge_Type":0,"Edge_Direction":0},{"Position":{"x":10.5,"y":6.0,"z":0.0},"Edge_Type":0,"Edge_Direction":0},{"Position":{"x":10.5,"y":7.0,"z":0.0},"Edge_Type":0,"Edge_Direction":0},{"Position":{"x":10.5,"y":8.0,"z":0.0},"Edge_Type":0,"Edge_Direction":0},{"Position":{"x":10.5,"y":9.0,"z":0.0},"Edge_Type":0,"Edge_Direction":0},{"Position":{"x":10.5,"y":10.0,"z":0.0},"Edge_Type":0,"Edge_Direction":0},{"Position":{"x":10.5,"y":11.0,"z":0.0},"Edge_Type":0,"Edge_Direction":0},{"Position":{"x":10.5,"y":12.0,"z":0.0},"Edge_Type":0,"Edge_Direction":0},{"Position":{"x":10.5,"y":13.0,"z":0.0},"Edge_Type":0,"Edge_Direction":0},{"Position":{"x":10.5,"y":14.0,"z":0.0},"Edge_Type":6,"Edge_Direction":0},{"Position":{"x":11.5,"y":0.0,"z":0.0},"Edge_Type":6,"Edge_Direction":0},{"Position":{"x":11.5,"y":1.0,"z":0.0},"Edge_Type":8,"Edge_Direction":0},{"Position":{"x":11.5,"y":2.0,"z":0.0},"Edge_Type":0,"Edge_Direction":0},{"Position":{"x":11.5,"y":3.0,"z":0.0},"Edge_Type":0,"Edge_Direction":0},{"Position":{"x":11.5,"y":4.0,"z":0.0},"Edge_Type":0,"Edge_Direction":0},{"Position":{"x":11.5,"y":5.0,"z":0.0},"Edge_Type":0,"Edge_Direction":0},{"Position":{"x":11.5,"y":6.0,"z":0.0},"Edge_Type":0,"Edge_Direction":0},{"Position":{"x":11.5,"y":7.0,"z":0.0},"Edge_Type":0,"Edge_Direction":0},{"Position":{"x":11.5,"y":8.0,"z":0.0},"Edge_Type":0,"Edge_Direction":0},{"Position":{"x":11.5,"y":9.0,"z":0.0},"Edge_Type":0,"Edge_Direction":0},{"Position":{"x":11.5,"y":10.0,"z":0.0},"Edge_Type":0,"Edge_Direction":0},{"Position":{"x":11.5,"y":11.0,"z":0.0},"Edge_Type":0,"Edge_Direction":0},{"Position":{"x":11.5,"y":12.0,"z":0.0},"Edge_Type":0,"Edge_Direction":0},{"Position":{"x":11.5,"y":13.0,"z":0.0},"Edge_Type":0,"Edge_Direction":0},{"Position":{"x":11.5,"y":14.0,"z":0.0},"Edge_Type":6,"Edge_Direction":0},{"Position":{"x":12.5,"y":0.0,"z":0.0},"Edge_Type":6,"Edge_Direction":0},{"Position":{"x":12.5,"y":1.0,"z":0.0},"Edge_Type":8,"Edge_Direction":0},{"Position":{"x":12.5,"y":2.0,"z":0.0},"Edge_Type":0,"Edge_Direction":0},{"Position":{"x":12.5,"y":3.0,"z":0.0},"Edge_Type":0,"Edge_Direction":0},{"Position":{"x":12.5,"y":4.0,"z":0.0},"Edge_Type":0,"Edge_Direction":0},{"Position":{"x":12.5,"y":5.0,"z":0.0},"Edge_Type":0,"Edge_Direction":0},{"Position":{"x":12.5,"y":6.0,"z":0.0},"Edge_Type":0,"Edge_Direction":0},{"Position":{"x":12.5,"y":7.0,"z":0.0},"Edge_Type":0,"Edge_Direction":0},{"Position":{"x":12.5,"y":8.0,"z":0.0},"Edge_Type":0,"Edge_Direction":0},{"Position":{"x":12.5,"y":9.0,"z":0.0},"Edge_Type":0,"Edge_Direction":0},{"Position":{"x":12.5,"y":10.0,"z":0.0},"Edge_Type":0,"Edge_Direction":0},{"Position":{"x":12.5,"y":11.0,"z":0.0},"Edge_Type":0,"Edge_Direction":0},{"Position":{"x":12.5,"y":12.0,"z":0.0},"Edge_Type":0,"Edge_Direction":0},{"Position":{"x":12.5,"y":13.0,"z":0.0},"Edge_Type":0,"Edge_Direction":0},{"Position":{"x":12.5,"y":14.0,"z":0.0},"Edge_Type":6,"Edge_Direction":0},{"Position":{"x":13.5,"y":0.0,"z":0.0},"Edge_Type":6,"Edge_Direction":0},{"Position":{"x":13.5,"y":1.0,"z":0.0},"Edge_Type":0,"Edge_Direction":0},{"Position":{"x":13.5,"y":2.0,"z":0.0},"Edge_Type":0,"Edge_Direction":0},{"Position":{"x":13.5,"y":3.0,"z":0.0},"Edge_Type":0,"Edge_Direction":0},{"Position":{"x":13.5,"y":4.0,"z":0.0},"Edge_Type":0,"Edge_Direction":0},{"Position":{"x":13.5,"y":5.0,"z":0.0},"Edge_Type":0,"Edge_Direction":0},{"Position":{"x":13.5,"y":6.0,"z":0.0},"Edge_Type":0,"Edge_Direction":0},{"Position":{"x":13.5,"y":7.0,"z":0.0},"Edge_Type":0,"Edge_Direction":0},{"Position":{"x":13.5,"y":8.0,"z":0.0},"Edge_Type":0,"Edge_Direction":0},{"Position":{"x":13.5,"y":9.0,"z":0.0},"Edge_Type":0,"Edge_Direction":0},{"Position":{"x":13.5,"y":10.0,"z":0.0},"Edge_Type":0,"Edge_Direction":0},{"Position":{"x":13.5,"y":11.0,"z":0.0},"Edge_Type":0,"Edge_Direction":0},{"Position":{"x":13.5,"y":12.0,"z":0.0},"Edge_Type":0,"Edge_Direction":0},{"Position":{"x":13.5,"y":13.0,"z":0.0},"Edge_Type":0,"Edge_Direction":0},{"Position":{"x":13.5,"y":14.0,"z":0.0},"Edge_Type":6,"Edge_Direction":0}],"LI_V_Edges":[{"Position":{"x":0.0,"y":0.5,"z":0.0},"Edge_Type":6,"Edge_Direction":1},{"Position":{"x":0.0,"y":1.5,"z":0.0},"Edge_Type":6,"Edge_Direction":1},{"Position":{"x":0.0,"y":2.5,"z":0.0},"Edge_Type":6,"Edge_Direction":1},{"Position":{"x":0.0,"y":3.5,"z":0.0},"Edge_Type":6,"Edge_Direction":1},{"Position":{"x":0.0,"y":4.5,"z":0.0},"Edge_Type":6,"Edge_Direction":1},{"Position":{"x":0.0,"y":5.5,"z":0.0},"Edge_Type":6,"Edge_Direction":1},{"Position":{"x":0.0,"y":6.5,"z":0.0},"Edge_Type":6,"Edge_Direction":1},{"Position":{"x":0.0,"y":7.5,"z":0.0},"Edge_Type":6,"Edge_Direction":1},{"Position":{"x":0.0,"y":8.5,"z":0.0},"Edge_Type":6,"Edge_Direction":1},{"Position":{"x":0.0,"y":9.5,"z":0.0},"Edge_Type":6,"Edge_Direction":1},{"Position":{"x":0.0,"y":10.5,"z":0.0},"Edge_Type":6,"Edge_Direction":1},{"Position":{"x":0.0,"y":11.5,"z":0.0},"Edge_Type":6,"Edge_Direction":1},{"Position":{"x":0.0,"y":12.5,"z":0.0},"Edge_Type":6,"Edge_Direction":1},{"Position":{"x":0.0,"y":13.5,"z":0.0},"Edge_Type":6,"Edge_Direction":1},{"Position":{"x":1.0,"y":0.5,"z":0.0},"Edge_Type":0,"Edge_Direction":1},{"Position":{"x":1.0,"y":1.5,"z":0.0},"Edge_Type":0,"Edge_Direction":1},{"Position":{"x":1.0,"y":2.5,"z":0.0},"Edge_Type":0,"Edge_Direction":1},{"Position":{"x":1.0,"y":3.5,"z":0.0},"Edge_Type":0,"Edge_Direction":1},{"Position":{"x":1.0,"y":4.5,"z":0.0},"Edge_Type":0,"Edge_Direction":1},{"Position":{"x":1.0,"y":5.5,"z":0.0},"Edge_Type":0,"Edge_Direction":1},{"Position":{"x":1.0,"y":6.5,"z":0.0},"Edge_Type":7,"Edge_Direction":1},{"Position":{"x":1.0,"y":7.5,"z":0.0},"Edge_Type":7,"Edge_Direction":1},{"Position":{"x":1.0,"y":8.5,"z":0.0},"Edge_Type":7,"Edge_Direction":1},{"Position":{"x":1.0,"y":9.5,"z":0.0},"Edge_Type":7,"Edge_Direction":1},{"Position":{"x":1.0,"y":10.5,"z":0.0},"Edge_Type":7,"Edge_Direction":1},{"Position":{"x":1.0,"y":11.5,"z":0.0},"Edge_Type":7,"Edge_Direction":1},{"Position":{"x":1.0,"y":12.5,"z":0.0},"Edge_Type":7,"Edge_Direction":1},{"Position":{"x":1.0,"y":13.5,"z":0.0},"Edge_Type":0,"Edge_Direction":1},{"Position":{"x":2.0,"y":0.5,"z":0.0},"Edge_Type":0,"Edge_Direction":1},{"Position":{"x":2.0,"y":1.5,"z":0.0},"Edge_Type":0,"Edge_Direction":1},{"Position":{"x":2.0,"y":2.5,"z":0.0},"Edge_Type":0,"Edge_Direction":1},{"Position":{"x":2.0,"y":3.5,"z":0.0},"Edge_Type":0,"Edge_Direction":1},{"Position":{"x":2.0,"y":4.5,"z":0.0},"Edge_Type":0,"Edge_Direction":1},{"Position":{"x":2.0,"y":5.5,"z":0.0},"Edge_Type":0,"Edge_Direction":1},{"Position":{"x":2.0,"y":6.5,"z":0.0},"Edge_Type":0,"Edge_Direction":1},{"Position":{"x":2.0,"y":7.5,"z":0.0},"Edge_Type":0,"Edge_Direction":1},{"Position":{"x":2.0,"y":8.5,"z":0.0},"Edge_Type":0,"Edge_Direction":1},{"Position":{"x":2.0,"y":9.5,"z":0.0},"Edge_Type":0,"Edge_Direction":1},{"Position":{"x":2.0,"y":10.5,"z":0.0},"Edge_Type":0,"Edge_Direction":1},{"Position":{"x":2.0,"y":11.5,"z":0.0},"Edge_Type":0,"Edge_Direction":1},{"Position":{"x":2.0,"y":12.5,"z":0.0},"Edge_Type":0,"Edge_Direction":1},{"Position":{"x":2.0,"y":13.5,"z":0.0},"Edge_Type":0,"Edge_Direction":1},{"Position":{"x":3.0,"y":0.5,"z":0.0},"Edge_Type":0,"Edge_Direction":1},{"Position":{"x":3.0,"y":1.5,"z":0.0},"Edge_Type":0,"Edge_Direction":1},{"Position":{"x":3.0,"y":2.5,"z":0.0},"Edge_Type":0,"Edge_Direction":1},{"Position":{"x":3.0,"y":3.5,"z":0.0},"Edge_Type":0,"Edge_Direction":1},{"Position":{"x":3.0,"y":4.5,"z":0.0},"Edge_Type":0,"Edge_Direction":1},{"Position":{"x":3.0,"y":5.5,"z":0.0},"Edge_Type":0,"Edge_Direction":1},{"Position":{"x":3.0,"y":6.5,"z":0.0},"Edge_Type":0,"Edge_Direction":1},{"Position":{"x":3.0,"y":7.5,"z":0.0},"Edge_Type":0,"Edge_Direction":1},{"Position":{"x":3.0,"y":8.5,"z":0.0},"Edge_Type":0,"Edge_Direction":1},{"Position":{"x":3.0,"y":9.5,"z":0.0},"Edge_Type":0,"Edge_Direction":1},{"Position":{"x":3.0,"y":10.5,"z":0.0},"Edge_Type":0,"Edge_Direction":1},{"Position":{"x":3.0,"y":11.5,"z":0.0},"Edge_Type":0,"Edge_Direction":1},{"Position":{"x":3.0,"y":12.5,"z":0.0},"Edge_Type":0,"Edge_Direction":1},{"Position":{"x":3.0,"y":13.5,"z":0.0},"Edge_Type":0,"Edge_Direction":1},{"Position":{"x":4.0,"y":0.5,"z":0.0},"Edge_Type":0,"Edge_Direction":1},{"Position":{"x":4.0,"y":1.5,"z":0.0},"Edge_Type":0,"Edge_Direction":1},{"Position":{"x":4.0,"y":2.5,"z":0.0},"Edge_Type":0,"Edge_Direction":1},{"Position":{"x":4.0,"y":3.5,"z":0.0},"Edge_Type":0,"Edge_Direction":1},{"Position":{"x":4.0,"y":4.5,"z":0.0},"Edge_Type":0,"Edge_Direction":1},{"Position":{"x":4.0,"y":5.5,"z":0.0},"Edge_Type":0,"Edge_Direction":1},{"Position":{"x":4.0,"y":6.5,"z":0.0},"Edge_Type":0,"Edge_Direction":1},{"Position":{"x":4.0,"y":7.5,"z":0.0},"Edge_Type":0,"Edge_Direction":1},{"Position":{"x":4.0,"y":8.5,"z":0.0},"Edge_Type":0,"Edge_Direction":1},{"Position":{"x":4.0,"y":9.5,"z":0.0},"Edge_Type":0,"Edge_Direction":1},{"Position":{"x":4.0,"y":10.5,"z":0.0},"Edge_Type":0,"Edge_Direction":1},{"Position":{"x":4.0,"y":11.5,"z":0.0},"Edge_Type":0,"Edge_Direction":1},{"Position":{"x":4.0,"y":12.5,"z":0.0},"Edge_Type":0,"Edge_Direction":1},{"Position":{"x":4.0,"y":13.5,"z":0.0},"Edge_Type":0,"Edge_Direction":1},{"Position":{"x":5.0,"y":0.5,"z":0.0},"Edge_Type":0,"Edge_Direction":1},{"Position":{"x":5.0,"y":1.5,"z":0.0},"Edge_Type":0,"Edge_Direction":1},{"Position":{"x":5.0,"y":2.5,"z":0.0},"Edge_Type":0,"Edge_Direction":1},{"Position":{"x":5.0,"y":3.5,"z":0.0},"Edge_Type":0,"Edge_Direction":1},{"Position":{"x":5.0,"y":4.5,"z":0.0},"Edge_Type":0,"Edge_Direction":1},{"Position":{"x":5.0,"y":5.5,"z":0.0},"Edge_Type":0,"Edge_Direction":1},{"Position":{"x":5.0,"y":6.5,"z":0.0},"Edge_Type":0,"Edge_Direction":1},{"Position":{"x":5.0,"y":7.5,"z":0.0},"Edge_Type":0,"Edge_Direction":1},{"Position":{"x":5.0,"y":8.5,"z":0.0},"Edge_Type":0,"Edge_Direction":1},{"Position":{"x":5.0,"y":9.5,"z":0.0},"Edge_Type":0,"Edge_Direction":1},{"Position":{"x":5.0,"y":10.5,"z":0.0},"Edge_Type":0,"Edge_Direction":1},{"Position":{"x":5.0,"y":11.5,"z":0.0},"Edge_Type":0,"Edge_Direction":1},{"Position":{"x":5.0,"y":12.5,"z":0.0},"Edge_Type":0,"Edge_Direction":1},{"Position":{"x":5.0,"y":13.5,"z":0.0},"Edge_Type":0,"Edge_Direction":1},{"Position":{"x":6.0,"y":0.5,"z":0.0},"Edge_Type":0,"Edge_Direction":1},{"Position":{"x":6.0,"y":1.5,"z":0.0},"Edge_Type":0,"Edge_Direction":1},{"Position":{"x":6.0,"y":2.5,"z":0.0},"Edge_Type":0,"Edge_Direction":1},{"Position":{"x":6.0,"y":3.5,"z":0.0},"Edge_Type":0,"Edge_Direction":1},{"Position":{"x":6.0,"y":4.5,"z":0.0},"Edge_Type":0,"Edge_Direction":1},{"Position":{"x":6.0,"y":5.5,"z":0.0},"Edge_Type":0,"Edge_Direction":1},{"Position":{"x":6.0,"y":6.5,"z":0.0},"Edge_Type":0,"Edge_Direction":1},{"Position":{"x":6.0,"y":7.5,"z":0.0},"Edge_Type":0,"Edge_Direction":1},{"Position":{"x":6.0,"y":8.5,"z":0.0},"Edge_Type":0,"Edge_Direction":1},{"Position":{"x":6.0,"y":9.5,"z":0.0},"Edge_Type":0,"Edge_Direction":1},{"Position":{"x":6.0,"y":10.5,"z":0.0},"Edge_Type":0,"Edge_Direction":1},{"Position":{"x":6.0,"y":11.5,"z":0.0},"Edge_Type":0,"Edge_Direction":1},{"Position":{"x":6.0,"y":12.5,"z":0.0},"Edge_Type":0,"Edge_Direction":1},{"Position":{"x":6.0,"y":13.5,"z":0.0},"Edge_Type":0,"Edge_Direction":1},{"Position":{"x":7.0,"y":0.5,"z":0.0},"Edge_Type":0,"Edge_Direction":1},{"Position":{"x":7.0,"y":1.5,"z":0.0},"Edge_Type":0,"Edge_Direction":1},{"Position":{"x":7.0,"y":2.5,"z":0.0},"Edge_Type":0,"Edge_Direction":1},{"Position":{"x":7.0,"y":3.5,"z":0.0},"Edge_Type":0,"Edge_Direction":1},{"Position":{"x":7.0,"y":4.5,"z":0.0},"Edge_Type":0,"Edge_Direction":1},{"Position":{"x":7.0,"y":5.5,"z":0.0},"Edge_Type":0,"Edge_Direction":1},{"Position":{"x":7.0,"y":6.5,"z":0.0},"Edge_Type":0,"Edge_Direction":1},{"Position":{"x":7.0,"y":7.5,"z":0.0},"Edge_Type":0,"Edge_Direction":1},{"Position":{"x":7.0,"y":8.5,"z":0.0},"Edge_Type":0,"Edge_Direction":1},{"Position":{"x":7.0,"y":9.5,"z":0.0},"Edge_Type":0,"Edge_Direction":1},{"Position":{"x":7.0,"y":10.5,"z":0.0},"Edge_Type":0,"Edge_Direction":1},{"Position":{"x":7.0,"y":11.5,"z":0.0},"Edge_Type":0,"Edge_Direction":1},{"Position":{"x":7.0,"y":12.5,"z":0.0},"Edge_Type":0,"Edge_Direction":1},{"Position":{"x":7.0,"y":13.5,"z":0.0},"Edge_Type":0,"Edge_Direction":1},{"Position":{"x":8.0,"y":0.5,"z":0.0},"Edge_Type":0,"Edge_Direction":1},{"Position":{"x":8.0,"y":1.5,"z":0.0},"Edge_Type":0,"Edge_Direction":1},{"Position":{"x":8.0,"y":2.5,"z":0.0},"Edge_Type":0,"Edge_Direction":1},{"Position":{"x":8.0,"y":3.5,"z":0.0},"Edge_Type":0,"Edge_Direction":1},{"Position":{"x":8.0,"y":4.5,"z":0.0},"Edge_Type":0,"Edge_Direction":1},{"Position":{"x":8.0,"y":5.5,"z":0.0},"Edge_Type":0,"Edge_Direction":1},{"Position":{"x":8.0,"y":6.5,"z":0.0},"Edge_Type":0,"Edge_Direction":1},{"Position":{"x":8.0,"y":7.5,"z":0.0},"Edge_Type":0,"Edge_Direction":1},{"Position":{"x":8.0,"y":8.5,"z":0.0},"Edge_Type":0,"Edge_Direction":1},{"Position":{"x":8.0,"y":9.5,"z":0.0},"Edge_Type":0,"Edge_Direction":1},{"Position":{"x":8.0,"y":10.5,"z":0.0},"Edge_Type":0,"Edge_Direction":1},{"Position":{"x":8.0,"y":11.5,"z":0.0},"Edge_Type":0,"Edge_Direction":1},{"Position":{"x":8.0,"y":12.5,"z":0.0},"Edge_Type":0,"Edge_Direction":1},{"Position":{"x":8.0,"y":13.5,"z":0.0},"Edge_Type":0,"Edge_Direction":1},{"Position":{"x":9.0,"y":0.5,"z":0.0},"Edge_Type":0,"Edge_Direction":1},{"Position":{"x":9.0,"y":1.5,"z":0.0},"Edge_Type":0,"Edge_Direction":1},{"Position":{"x":9.0,"y":2.5,"z":0.0},"Edge_Type":0,"Edge_Direction":1},{"Position":{"x":9.0,"y":3.5,"z":0.0},"Edge_Type":0,"Edge_Direction":1},{"Position":{"x":9.0,"y":4.5,"z":0.0},"Edge_Type":0,"Edge_Direction":1},{"Position":{"x":9.0,"y":5.5,"z":0.0},"Edge_Type":0,"Edge_Direction":1},{"Position":{"x":9.0,"y":6.5,"z":0.0},"Edge_Type":0,"Edge_Direction":1},{"Position":{"x":9.0,"y":7.5,"z":0.0},"Edge_Type":0,"Edge_Direction":1},{"Position":{"x":9.0,"y":8.5,"z":0.0},"Edge_Type":0,"Edge_Direction":1},{"Position":{"x":9.0,"y":9.5,"z":0.0},"Edge_Type":0,"Edge_Direction":1},{"Position":{"x":9.0,"y":10.5,"z":0.0},"Edge_Type":0,"Edge_Direction":1},{"Position":{"x":9.0,"y":11.5,"z":0.0},"Edge_Type":0,"Edge_Direction":1},{"Position":{"x":9.0,"y":12.5,"z":0.0},"Edge_Type":0,"Edge_Direction":1},{"Position":{"x":9.0,"y":13.5,"z":0.0},"Edge_Type":0,"Edge_Direction":1},{"Position":{"x":10.0,"y":0.5,"z":0.0},"Edge_Type":0,"Edge_Direction":1},{"Position":{"x":10.0,"y":1.5,"z":0.0},"Edge_Type":0,"Edge_Direction":1},{"Position":{"x":10.0,"y":2.5,"z":0.0},"Edge_Type":0,"Edge_Direction":1},{"Position":{"x":10.0,"y":3.5,"z":0.0},"Edge_Type":0,"Edge_Direction":1},{"Position":{"x":10.0,"y":4.5,"z":0.0},"Edge_Type":0,"Edge_Direction":1},{"Position":{"x":10.0,"y":5.5,"z":0.0},"Edge_Type":0,"Edge_Direction":1},{"Position":{"x":10.0,"y":6.5,"z":0.0},"Edge_Type":0,"Edge_Direction":1},{"Position":{"x":10.0,"y":7.5,"z":0.0},"Edge_Type":0,"Edge_Direction":1},{"Position":{"x":10.0,"y":8.5,"z":0.0},"Edge_Type":0,"Edge_Direction":1},{"Position":{"x":10.0,"y":9.5,"z":0.0},"Edge_Type":0,"Edge_Direction":1},{"Position":{"x":10.0,"y":10.5,"z":0.0},"Edge_Type":0,"Edge_Direction":1},{"Position":{"x":10.0,"y":11.5,"z":0.0},"Edge_Type":0,"Edge_Direction":1},{"Position":{"x":10.0,"y":12.5,"z":0.0},"Edge_Type":0,"Edge_Direction":1},{"Position":{"x":10.0,"y":13.5,"z":0.0},"Edge_Type":0,"Edge_Direction":1},{"Position":{"x":11.0,"y":0.5,"z":0.0},"Edge_Type":0,"Edge_Direction":1},{"Position":{"x":11.0,"y":1.5,"z":0.0},"Edge_Type":0,"Edge_Direction":1},{"Position":{"x":11.0,"y":2.5,"z":0.0},"Edge_Type":0,"Edge_Direction":1},{"Position":{"x":11.0,"y":3.5,"z":0.0},"Edge_Type":0,"Edge_Direction":1},{"Position":{"x":11.0,"y":4.5,"z":0.0},"Edge_Type":0,"Edge_Direction":1},{"Position":{"x":11.0,"y":5.5,"z":0.0},"Edge_Type":0,"Edge_Direction":1},{"Position":{"x":11.0,"y":6.5,"z":0.0},"Edge_Type":0,"Edge_Direction":1},{"Position":{"x":11.0,"y":7.5,"z":0.0},"Edge_Type":0,"Edge_Direction":1},{"Position":{"x":11.0,"y":8.5,"z":0.0},"Edge_Type":0,"Edge_Direction":1},{"Position":{"x":11.0,"y":9.5,"z":0.0},"Edge_Type":0,"Edge_Direction":1},{"Position":{"x":11.0,"y":10.5,"z":0.0},"Edge_Type":0,"Edge_Direction":1},{"Position":{"x":11.0,"y":11.5,"z":0.0},"Edge_Type":0,"Edge_Direction":1},{"Position":{"x":11.0,"y":12.5,"z":0.0},"Edge_Type":0,"Edge_Direction":1},{"Position":{"x":11.0,"y":13.5,"z":0.0},"Edge_Type":0,"Edge_Direction":1},{"Position":{"x":12.0,"y":0.5,"z":0.0},"Edge_Type":0,"Edge_Direction":1},{"Position":{"x":12.0,"y":1.5,"z":0.0},"Edge_Type":0,"Edge_Direction":1},{"Position":{"x":12.0,"y":2.5,"z":0.0},"Edge_Type":0,"Edge_Direction":1},{"Position":{"x":12.0,"y":3.5,"z":0.0},"Edge_Type":0,"Edge_Direction":1},{"Position":{"x":12.0,"y":4.5,"z":0.0},"Edge_Type":0,"Edge_Direction":1},{"Position":{"x":12.0,"y":5.5,"z":0.0},"Edge_Type":0,"Edge_Direction":1},{"Position":{"x":12.0,"y":6.5,"z":0.0},"Edge_Type":0,"Edge_Direction":1},{"Position":{"x":12.0,"y":7.5,"z":0.0},"Edge_Type":0,"Edge_Direction":1},{"Position":{"x":12.0,"y":8.5,"z":0.0},"Edge_Type":0,"Edge_Direction":1},{"Position":{"x":12.0,"y":9.5,"z":0.0},"Edge_Type":0,"Edge_Direction":1},{"Position":{"x":12.0,"y":10.5,"z":0.0},"Edge_Type":0,"Edge_Direction":1},{"Position":{"x":12.0,"y":11.5,"z":0.0},"Edge_Type":0,"Edge_Direction":1},{"Position":{"x":12.0,"y":12.5,"z":0.0},"Edge_Type":0,"Edge_Direction":1},{"Position":{"x":12.0,"y":13.5,"z":0.0},"Edge_Type":0,"Edge_Direction":1},{"Position":{"x":13.0,"y":0.5,"z":0.0},"Edge_Type":0,"Edge_Direction":1},{"Position":{"x":13.0,"y":1.5,"z":0.0},"Edge_Type":8,"Edge_Direction":1},{"Position":{"x":13.0,"y":2.5,"z":0.0},"Edge_Type":8,"Edge_Direction":1},{"Position":{"x":13.0,"y":3.5,"z":0.0},"Edge_Type":8,"Edge_Direction":1},{"Position":{"x":13.0,"y":4.5,"z":0.0},"Edge_Type":8,"Edge_Direction":1},{"Position":{"x":13.0,"y":5.5,"z":0.0},"Edge_Type":8,"Edge_Direction":1},{"Position":{"x":13.0,"y":6.5,"z":0.0},"Edge_Type":8,"Edge_Direction":1},{"Position":{"x":13.0,"y":7.5,"z":0.0},"Edge_Type":8,"Edge_Direction":1},{"Position":{"x":13.0,"y":8.5,"z":0.0},"Edge_Type":0,"Edge_Direction":1},{"Position":{"x":13.0,"y":9.5,"z":0.0},"Edge_Type":0,"Edge_Direction":1},{"Position":{"x":13.0,"y":10.5,"z":0.0},"Edge_Type":0,"Edge_Direction":1},{"Position":{"x":13.0,"y":11.5,"z":0.0},"Edge_Type":0,"Edge_Direction":1},{"Position":{"x":13.0,"y":12.5,"z":0.0},"Edge_Type":0,"Edge_Direction":1},{"Position":{"x":13.0,"y":13.5,"z":0.0},"Edge_Type":0,"Edge_Direction":1},{"Position":{"x":14.0,"y":0.5,"z":0.0},"Edge_Type":6,"Edge_Direction":1},{"Position":{"x":14.0,"y":1.5,"z":0.0},"Edge_Type":6,"Edge_Direction":1},{"Position":{"x":14.0,"y":2.5,"z":0.0},"Edge_Type":6,"Edge_Direction":1},{"Position":{"x":14.0,"y":3.5,"z":0.0},"Edge_Type":6,"Edge_Direction":1},{"Position":{"x":14.0,"y":4.5,"z":0.0},"Edge_Type":6,"Edge_Direction":1},{"Position":{"x":14.0,"y":5.5,"z":0.0},"Edge_Type":6,"Edge_Direction":1},{"Position":{"x":14.0,"y":6.5,"z":0.0},"Edge_Type":6,"Edge_Direction":1},{"Position":{"x":14.0,"y":7.5,"z":0.0},"Edge_Type":6,"Edge_Direction":1},{"Position":{"x":14.0,"y":8.5,"z":0.0},"Edge_Type":6,"Edge_Direction":1},{"Position":{"x":14.0,"y":9.5,"z":0.0},"Edge_Type":6,"Edge_Direction":1},{"Position":{"x":14.0,"y":10.5,"z":0.0},"Edge_Type":6,"Edge_Direction":1},{"Position":{"x":14.0,"y":11.5,"z":0.0},"Edge_Type":6,"Edge_Direction":1},{"Position":{"x":14.0,"y":12.5,"z":0.0},"Edge_Type":6,"Edge_Direction":1},{"Position":{"x":14.0,"y":13.5,"z":0.0},"Edge_Type":6,"Edge_Direction":1}],"Cam":{"Position":{"x":7.0,"y":7.0,"z":-20.0},"Size":7.512053489685059}}